lab9/ejercicio 1/ej1.v
// lab 9

// ejercicio 01
module flipflopD(input wire CLK, reset, D, enable, output reg Q);

always @ (posedge CLK, posedge reset, enable) begin
	if (reset) begin
		Q <= 1'b0;
	end
	else if (enable) begin
		Q <= D;
	end
end
endmodule

module flipflopD2(input wire clk, reset, enable, input wire [0:1]d, output wire [0:1]q);
	flipflopD f1(clk, reset, d[0], enable, q[0]);
	flipflopD f2(clk, reset, d[1], enable, q[1]);
endmodule

module flipflopD4(input wire clk, reset, enable, input wire [0:3]d, output wire [0:3]q);

	flipflopD ff1(clk, reset, d[0], enable, q[0]);
	flipflopD ff2(clk, reset, d[1], enable, q[1]);
	flipflopD ff3(clk, reset, d[2], enable, q[2]);
	flipflopD ff4(clk, reset, d[3], enable, q[3]);

endmodule

lab9/ejercicio 1/ej1_tb.v
module testbench();

reg clk, reset, enable, d1;
wire q1, qt;
reg 	[0:1]d2;
wire	[0:1]q2;
reg		[0:3]d4;
wire	[0:3]q4;

flipflopD	f1(clk, reset, d1, enable, q1);
flipflopD2	f2(clk, reset, enable, d2, q2);
flipflopD4	f4(clk, reset, enable, d4, q4);

	always
		begin
		clk <= 0; #1 clk <=1; #1;
		end

initial begin
#1
	$display("\n flipflop d");
	$display("clk reset enable  d1 | q1");
	$monitor("%b     %b     %b     %b  |  %b", clk, reset, enable, d1, q1);
	#1	reset = 1;	d1 = 0;
	#1	reset = 0;
	#1	enable = 0;	d1 = 1;
	#2	enable = 1;	
	#2	d1 = 0;
end

initial begin
#10
	$display("\n flipflop d \n 2 bits");
	$display("clk reset enable   d2 | q2");
	$monitor("%b     %b     %b     %b  |  %b", clk, reset, enable, d2, q2);
	#1	reset = 1;	d2 = 2'b01; enable = 0;
	#1	reset = 0;
	#1	enable = 0;	d2 = 2'b11;
	#2	enable = 1;
	#3	d2 = 2'b00;	
end

initial begin
#24
	$display("\n flipflop d \n 4 bits");
	$display("clk reset enable    d4 | q4");
	$monitor("%b     %b     %b     %b  |  %b", clk, reset, enable, d4, q4);
	#1	reset = 1;	d4 = 4'b1010;
	#1	reset = 0;
	#1	enable = 0;	d4 = 4'b1111;
	#2	enable = 1;	
	#3	enable = 0;
	#2	d4 = 4'b0001;
	#3	enable = 1;
	#4	d4 = 4'b0110;
end


initial
	#45	$finish;
	initial begin
		$dumpfile("ej1.vcd");
		$dumpvars(0, testbench);
	end
endmodule

lab9/ejercicio 1/ej1.vcd
$date
	Sat Oct 31 10:17:28 2020
$end
$version
	Icarus Verilog
$end
$timescale
	1ps
$end
$scope module testbench $end
$var wire 4 ! q4 [0:3] $end
$var wire 2 " q2 [0:1] $end
$var wire 1 # q1 $end
$var reg 1 $ clk $end
$var reg 1 % d1 $end
$var reg 2 & d2 [0:1] $end
$var reg 4 ' d4 [0:3] $end
$var reg 1 ( enable $end
$var reg 1 ) reset $end
$scope module f1 $end
$var wire 1 $ CLK $end
$var wire 1 % D $end
$var wire 1 ( enable $end
$var wire 1 ) reset $end
$var reg 1 # Q $end
$upscope $end
$scope module f2 $end
$var wire 1 $ clk $end
$var wire 2 * d [0:1] $end
$var wire 1 ( enable $end
$var wire 1 ) reset $end
$var wire 2 + q [0:1] $end
$scope module f1 $end
$var wire 1 $ CLK $end
$var wire 1 , D $end
$var wire 1 ( enable $end
$var wire 1 ) reset $end
$var reg 1 - Q $end
$upscope $end
$scope module f2 $end
$var wire 1 $ CLK $end
$var wire 1 . D $end
$var wire 1 ( enable $end
$var wire 1 ) reset $end
$var reg 1 / Q $end
$upscope $end
$upscope $end
$scope module f4 $end
$var wire 1 $ clk $end
$var wire 4 0 d [0:3] $end
$var wire 1 ( enable $end
$var wire 1 ) reset $end
$var wire 4 1 q [0:3] $end
$scope module ff1 $end
$var wire 1 $ CLK $end
$var wire 1 2 D $end
$var wire 1 ( enable $end
$var wire 1 ) reset $end
$var reg 1 3 Q $end
$upscope $end
$scope module ff2 $end
$var wire 1 $ CLK $end
$var wire 1 4 D $end
$var wire 1 ( enable $end
$var wire 1 ) reset $end
$var reg 1 5 Q $end
$upscope $end
$scope module ff3 $end
$var wire 1 $ CLK $end
$var wire 1 6 D $end
$var wire 1 ( enable $end
$var wire 1 ) reset $end
$var reg 1 7 Q $end
$upscope $end
$scope module ff4 $end
$var wire 1 $ CLK $end
$var wire 1 8 D $end
$var wire 1 ( enable $end
$var wire 1 ) reset $end
$var reg 1 9 Q $end
$upscope $end
$upscope $end
$upscope $end
$enddefinitions $end
#0
$dumpvars
x9
x8
x7
x6
x5
x4
x3
x2
bx 1
bx 0
x/
x.
x-
x,
bx +
bx *
x)
x(
bx '
bx &
x%
0$
x#
bx "
bx !
$end
#1
1$
#2
09
07
05
b0 !
b0 1
03
0/
b0 "
b0 +
0-
0#
0$
0%
1)
#3
1$
0)
#4
0$
1%
0(
#5
1$
#6
x9
x7
x5
bx !
bx 1
x3
x/
bx "
bx +
x-
1#
0$
1(
#7
1$
#8
0$
0%
#9
0#
1$
#10
0$
#11
0-
b0 "
b0 +
0/
03
05
07
b0 !
b0 1
09
1$
0,
1.
0(
b1 &
b1 *
1)
#12
0$
0)
#13
1$
1,
b11 &
b11 *
#14
0$
#15
x9
x7
x5
bx !
bx 1
x3
1/
b11 "
b11 +
1-
1$
1(
#16
0$
#17
1$
#18
0$
0,
0.
b0 &
b0 *
#19
0-
b0 "
b0 +
0/
1$
#20
0$
#21
1$
#22
0$
#23
1$
#24
0$
#25
09
07
05
b0 !
b0 1
03
1$
12
04
16
08
b1010 '
b1010 0
1)
#26
0$
0)
#27
1$
14
18
b1111 '
b1111 0
0(
#28
0$
#29
19
17
15
b1111 !
b1111 1
13
1$
1(
#30
0$
#31
1$
#32
0$
0(
#33
1$
#34
0$
02
04
06
b1 '
b1 0
#35
1$
#36
0$
#37
07
05
b1 !
b1 1
03
1$
1(
#38
0$
#39
1$
#40
0$
#41
15
17
b110 !
b110 1
09
1$
14
16
08
b110 '
b110 0
