lab6/set síncrono/ejercicio5_2.v


// síncrono set
module flipflop2(input wire CLK,reset,set, input wire [3:0]D, output reg [3:0]Q);


always @ (posedge CLK, posedge reset, posedge set) begin
	if(reset) begin
		Q <= 4'b0;
	end
	else if (set) begin
	Q <= 4'b1111;
	end
	else begin
		Q <= D;
	end
end

endmodule

lab6/set síncrono/ejercicio5_2_tb.v
// flip flop con set síncrono

module testbench();
reg CLK, reset, set; 
reg [3:0]D;
wire [3:0]Q;

initial begin
	CLK = 0;

	forever #1 CLK = ~CLK;
end

flipflop2 U2(CLK,reset,set,D,Q);

initial begin
#1
$display("\n");
$display("R  S    CLK    D      Q");
$monitor("%b   %b   %b   %b     %b", reset, set, CLK, D, Q);
		D=0000; reset = 1; set = 0;
	#1 	D=0101; reset = 0;
	#1	D=1100;
	#2	D=0101;	set = 1; 
	#1	D=1111; reset=1; set = 0;
	#1	D=0110;
	#1	D=1110;
	#1	D=1111; reset=0;
	#2	D=0111;
	#1	D=1010;
end

initial
	#25 $finish;

	initial begin
		$dumpfile("lab6.vcd");
		$dumpvars(0, testbench);
	end


endmodule

lab6/set síncrono/lab6.vcd
$date
	Sat Sep  5 06:20:32 2020
$end
$version
	Icarus Verilog
$end
$timescale
	1ps
$end
$scope module testbench $end
$var wire 4 ! Q [3:0] $end
$var reg 1 " CLK $end
$var reg 4 # D [3:0] $end
$var reg 1 $ reset $end
$var reg 1 % set $end
$scope module U2 $end
$var wire 1 " CLK $end
$var wire 4 & D [3:0] $end
$var wire 1 $ reset $end
$var wire 1 % set $end
$var reg 4 ' Q [3:0] $end
$upscope $end
$upscope $end
$enddefinitions $end
#0
$dumpvars
bx '
bx &
x%
x$
bx #
0"
bx !
$end
#1
b0 !
b0 '
0%
1$
b0 #
b0 &
1"
#2
0$
b101 #
b101 &
0"
#3
b1100 !
b1100 '
b1100 #
b1100 &
1"
#4
0"
#5
b1111 !
b1111 '
1"
1%
b101 #
b101 &
#6
b0 !
b0 '
0"
0%
1$
b111 #
b111 &
#7
1"
b1110 #
b1110 &
#8
0"
b110 #
b110 &
#9
b111 !
b111 '
1"
0$
b111 #
b111 &
#10
0"
#11
b1111 !
b1111 '
1"
b1111 #
b1111 &
#12
0"
b10 #
b10 &
#13
b10 !
b10 '
1"
