lab3/tabla04SOP/tabla04SOP.v
module tabla04SOP();

// POS del tabla04

  reg A, B, C, D;
  wire w1, w2, w3, w4, w5, w6, w7, out, wa, wb, wc, wd;
  
  not U1(wa, A);
  not U2(wb, B);
  not U3(wc, C);
  not U4(wd, D);
  and U5(w1, wa, wb, wc, wd);
  and U6(w2, wa, wb, C, wd);
  and U7(w3, wa, wb, C, D);
  and U8(w4, wa, B, C, wd);
  and U9(w5, wa, B, C, D);
  and U10(w6, A, wb, wc, wd);
  and U11(w7, A, wb, C, wd);
  or U12(out, w1, w2, w3, w4, w5, w6, w7);


  initial begin
    $display("A B C D| Y");
    $display("-------");
    $monitor("%b %b %b %b | %b", A, B, C, D, out);
    A = 0; B = 0; C=0; D=0;
    #1 D = 1;
    #1 C = 1; D = 0;
    #1 D = 1;
    #1 B = 1; C = 0; D = 0;
    #1 D = 1;
    #1 C = 1; D = 0;
    #1 D = 1;
    #1 A = 1; B = 0; C = 0; D = 0;
    #1 D = 1;
    #1 C = 1; D = 0;
    #1 D = 1;
    #1 B = 1; C = 0; D = 0;
    #1 D = 1;
    #1 C = 1; D = 0;
    #1 D = 1;
    #1 $finish;
  end

  initial begin
      $dumpfile("tabla04SOP.vcd"); 
      $dumpvars(0, tabla04SOP);
    end 

endmodule

lab3/tabla04SOP/tabla04SOP.vcd
$date
	Sun Aug  2 14:51:18 2020
$end
$version
	Icarus Verilog
$end
$timescale
	1ps
$end
$scope module tabla04SOP $end
$var wire 1 ! out $end
$var wire 1 " w1 $end
$var wire 1 # w2 $end
$var wire 1 $ w3 $end
$var wire 1 % w4 $end
$var wire 1 & w5 $end
$var wire 1 ' w6 $end
$var wire 1 ( w7 $end
$var wire 1 ) wa $end
$var wire 1 * wb $end
$var wire 1 + wc $end
$var wire 1 , wd $end
$var reg 1 - A $end
$var reg 1 . B $end
$var reg 1 / C $end
$var reg 1 0 D $end
$upscope $end
$enddefinitions $end
#0
$dumpvars
00
0/
0.
0-
1,
1+
1*
1)
0(
0'
0&
0%
0$
0#
1"
1!
$end
#1
0!
0"
0,
10
#2
1!
1#
1,
0+
00
1/
#3
0#
1$
0,
10
#4
0!
1,
0$
1+
0*
00
0/
1.
#5
0,
10
#6
1!
1%
1,
0+
00
1/
#7
0%
1&
0,
10
#8
1'
1,
1+
0&
1*
0)
00
0/
0.
1-
#9
0!
0'
0,
10
#10
1!
1(
1,
0+
00
1/
#11
0!
0(
0,
10
#12
1,
1+
0*
00
0/
1.
#13
0,
10
#14
1,
0+
00
1/
#15
0,
10
