lab3/tabla01POS/tabla01POS.v
module tabla01POS();

// POS del tabla01POS

  reg A, B, C;
  wire w1, w2, w3, out, wa, wb, wc;

  // not (salida, entrada);
  // and (salida, entrada1, entrada2, entrada3, etc);
  
  not U1(wa, A);
  not U2(wb, B);
  not U3(wc, C);
  or U1(w1, A, B, wc);
  or U2(w2, A, wb, wc);
  or U3(w3, wb, C, wa);
  and U4(out, w1, w2, w3);


  initial begin
    $display("A B C | Y");
    $display("-------");
    $monitor("%b %b %b | %b", A, B, C, out);
    A = 0; B = 0; C=0;
    #1 C = 1;
    #1 B = 1;
    C = 0;
    #1 B = 1;
    C = 1;
    #1 A = 1;
    B = 0;
    C = 0;
     #1 C = 1;
    #1 B = 1;
    C = 0;
    #1 B = 1;
    C = 1;
    #1 $finish;
  end

  initial begin
      $dumpfile("tabla01POS.vcd"); 
      $dumpvars(0, tabla01POS);
    end 

endmodule

lab3/tabla01POS/tabla01POS.vcd
$date
	Sun Aug  2 17:12:36 2020
$end
$version
	Icarus Verilog
$end
$timescale
	1ps
$end
$scope module tabla01POS $end
$var wire 1 ! out $end
$var wire 1 " w1 $end
$var wire 1 # w2 $end
$var wire 1 $ w3 $end
$var wire 1 % wa $end
$var wire 1 & wb $end
$var wire 1 ' wc $end
$var reg 1 ( A $end
$var reg 1 ) B $end
$var reg 1 * C $end
$upscope $end
$enddefinitions $end
#0
$dumpvars
0*
0)
0(
1'
1&
1%
1$
1#
1"
1!
$end
#1
0!
0"
0'
1*
#2
1!
1'
1"
0&
0*
1)
#3
0!
0#
0'
1*
#4
1!
1'
1&
1#
0%
0*
0)
1(
#5
0'
1*
#6
0!
0$
1'
0&
0*
1)
#7
1!
1$
0'
1*
