lab10/ejercicio1/ejercicio1.v
// -----------------------------------------------------------------------------
//	Daniela Morales Ponce
//	laboratorio 10
//	ejercicio1
// -----------------------------------------------------------------------------

module pc_counter(
    input clk, reset, enable, load, input[0:11]loadbits,
    output reg[0:11] count
);

always @ (posedge clk, posedge reset, posedge load) begin


if(enable) begin
    	count <= count + 1'b1;
	end

if(load) begin
	count <= loadbits;
	end

if(reset) begin
	count <= 000000000000;
	end

end
endmodule

module ROM(
	input logic [0:11] adress,
	output wire [0:7] data);
reg[0:11] memoria [0:4095];

initial begin
	$readmemh("memory_list", memoria);
	end
assign	data = memoria[adress];
endmodule

module flipflopD(input wire CLK, reset, D, enable, output reg Q);

always @ (posedge CLK, posedge reset, enable) begin
	if (reset) begin
		Q <= 1'b0;
	end
	else if (enable) begin
		Q <= D;
	end
end
endmodule

module flipflopD4(input wire clk, reset, enable, input wire [0:7]prog_byte, output wire [0:3]instr, output wire [0:3]oprnd);

	flipflopD ff1(clk, reset, prog_byte[0], enable, instr[0]);
	flipflopD ff2(clk, reset, prog_byte[1], enable, instr[1]);
	flipflopD ff3(clk, reset, prog_byte[2], enable, instr[2]);
	flipflopD ff4(clk, reset, prog_byte[3], enable, instr[3]);

	flipflopD ff5(clk, reset, prog_byte[4], enable, oprnd[0]);
	flipflopD ff6(clk, reset, prog_byte[5], enable, oprnd[1]);
	flipflopD ff7(clk, reset, prog_byte[6], enable, oprnd[2]);
	flipflopD ff8(clk, reset, prog_byte[7], enable, oprnd[3]);

endmodule

module ejercicio1 (
	input	clk,    			// Clock
	input	pc_en, 				// program counter Enable
	input	fetch_en, 			// fecth enable
	input	reset,  			// reset ff y pc
	input 	[0:11]loadbits,		// load pc
	input	load,				// load bit
	output	[0:7]data,		// program byte 
	output	[0:3]instr,
	output	[0:3]oprnd
);
	wire [0:11] address;

	pc_counter i_pc_counter (
		.clk(clk), 
		.reset(reset), 
		.enable(pc_en), 
		.load(load), 
		.loadbits(loadbits), 
		.count(address)
	);


	ROM i_ROM (
		.adress(address), 
		.data(data)
	);


	flipflopD4 i_flipflopD4 (
		.clk      (clk),
		.reset    (reset),
		.enable   (fetch_en),
		.prog_byte(data),
		.instr    (instr),
		.oprnd    (oprnd)
	);
endmodule

lab10/ejercicio1/ejercicio1_tb.v
module testbench();

reg clk;
reg pc_en;
reg fetch_en;
reg reset;
reg [0:11] loadbits;
reg load;
wire [0:7] data;
wire [0:3] instr;
wire [0:3] oprnd;

		ejercicio1 i_ejercicio1 (
			.clk     (clk     ),
			.pc_en   (pc_en   ),
			.fetch_en(fetch_en),
			.reset   (reset   ),
			.loadbits(loadbits),
			.load    (load    ),
			.data    (data    ),
			.instr   (instr   ),
			.oprnd   (oprnd   )
		);

always
	begin
	clk <= 0; #1 clk <=1; #1;
end

initial begin
#1
	$display("\n ejercicio1");
	$display("|clk e_pc e_fetch reset  loadbits    load |program byte   instr  oprnd");
	$monitor("|  %b   %b    %b      %b    %b    %b | %b       %b  %b", clk, pc_en, fetch_en, reset, loadbits, load, data, instr, oprnd);
	#1	reset = 1; pc_en = 1; fetch_en = 1; load = 0; loadbits = 12'h000;
	#1	reset = 0;
	#5	loadbits = 12'h003;
	#3	load = 1;
	#5	load = 0;
	#5	fetch_en = 0;
	#4	pc_en = 0; 
	#3	fetch_en = 1;
	#5	reset = 1;
	#4	reset = 0; pc_en = 1; fetch_en = 1; loadbits = 12'h0A1;
	#1	load = 1;
	#1	load = 0;
end

initial
	#45	$finish;
	initial begin
		$dumpfile("ejercicio1.vcd");
		$dumpvars(0, testbench);
	end
endmodule

lab10/ejercicio1/ejercicio1.vcd
$date
	Sat Nov  7 13:52:46 2020
$end
$version
	Icarus Verilog
$end
$timescale
	1ps
$end
$scope module testbench $end
$var wire 4 ! oprnd [0:3] $end
$var wire 4 " instr [0:3] $end
$var wire 8 # data [0:7] $end
$var reg 1 $ clk $end
$var reg 1 % fetch_en $end
$var reg 1 & load $end
$var reg 12 ' loadbits [0:11] $end
$var reg 1 ( pc_en $end
$var reg 1 ) reset $end
$scope module i_ejercicio1 $end
$var wire 1 $ clk $end
$var wire 1 % fetch_en $end
$var wire 1 & load $end
$var wire 12 * loadbits [0:11] $end
$var wire 1 ( pc_en $end
$var wire 1 ) reset $end
$var wire 4 + oprnd [0:3] $end
$var wire 4 , instr [0:3] $end
$var wire 8 - data [0:7] $end
$var wire 12 . address [0:11] $end
$scope module i_ROM $end
$var wire 8 / data [0:7] $end
$var wire 12 0 adress [0:11] $end
$upscope $end
$scope module i_flipflopD4 $end
$var wire 1 $ clk $end
$var wire 1 % enable $end
$var wire 8 1 prog_byte [0:7] $end
$var wire 1 ) reset $end
$var wire 4 2 oprnd [0:3] $end
$var wire 4 3 instr [0:3] $end
$scope module ff1 $end
$var wire 1 $ CLK $end
$var wire 1 4 D $end
$var wire 1 % enable $end
$var wire 1 ) reset $end
$var reg 1 5 Q $end
$upscope $end
$scope module ff2 $end
$var wire 1 $ CLK $end
$var wire 1 6 D $end
$var wire 1 % enable $end
$var wire 1 ) reset $end
$var reg 1 7 Q $end
$upscope $end
$scope module ff3 $end
$var wire 1 $ CLK $end
$var wire 1 8 D $end
$var wire 1 % enable $end
$var wire 1 ) reset $end
$var reg 1 9 Q $end
$upscope $end
$scope module ff4 $end
$var wire 1 $ CLK $end
$var wire 1 : D $end
$var wire 1 % enable $end
$var wire 1 ) reset $end
$var reg 1 ; Q $end
$upscope $end
$scope module ff5 $end
$var wire 1 $ CLK $end
$var wire 1 < D $end
$var wire 1 % enable $end
$var wire 1 ) reset $end
$var reg 1 = Q $end
$upscope $end
$scope module ff6 $end
$var wire 1 $ CLK $end
$var wire 1 > D $end
$var wire 1 % enable $end
$var wire 1 ) reset $end
$var reg 1 ? Q $end
$upscope $end
$scope module ff7 $end
$var wire 1 $ CLK $end
$var wire 1 @ D $end
$var wire 1 % enable $end
$var wire 1 ) reset $end
$var reg 1 A Q $end
$upscope $end
$scope module ff8 $end
$var wire 1 $ CLK $end
$var wire 1 B D $end
$var wire 1 % enable $end
$var wire 1 ) reset $end
$var reg 1 C Q $end
$upscope $end
$upscope $end
$scope module i_pc_counter $end
$var wire 1 $ clk $end
$var wire 1 ( enable $end
$var wire 1 & load $end
$var wire 12 D loadbits [0:11] $end
$var wire 1 ) reset $end
$var reg 12 E count [0:11] $end
$upscope $end
$upscope $end
$upscope $end
$enddefinitions $end
#0
$dumpvars
bx E
bx D
xC
xB
xA
x@
x?
x>
x=
x<
x;
x:
x9
x8
x7
x6
x5
x4
bx 3
bx 2
bx 1
bx 0
bx /
bx .
bx -
bx ,
bx +
bx *
x)
x(
bx '
x&
x%
0$
bx #
bx "
bx !
$end
#1
1$
#2
04
06
08
0:
0<
0>
0@
0B
b0 #
b0 -
b0 /
b0 1
0C
0A
0?
b0 !
b0 +
b0 2
0=
0;
09
07
b0 "
b0 ,
b0 3
05
b0 .
b0 0
b0 E
0$
b0 '
b0 *
b0 D
0&
1%
1(
1)
#3
1B
b1 #
b1 -
b1 /
b1 1
b1 .
b1 0
b1 E
1$
0)
#4
0$
#5
1@
0B
b10 #
b10 -
b10 /
b10 1
b1 !
b1 +
b1 2
1C
b10 .
b10 0
b10 E
1$
#6
0$
#7
1B
b11 #
b11 -
b11 /
b11 1
1A
b10 !
b10 +
b10 2
0C
b11 .
b11 0
b11 E
1$
#8
0$
b11 '
b11 *
b11 D
#9
1>
0@
0B
b100 #
b100 -
b100 /
b100 1
b11 !
b11 +
b11 2
1C
b100 .
b100 0
b100 E
1$
#10
0$
#11
1?
0A
b100 !
b100 +
b100 2
0C
0>
1@
1B
b11 #
b11 -
b11 /
b11 1
b11 .
b11 0
b11 E
1$
1&
#12
0$
#13
1C
1A
b11 !
b11 +
b11 2
0?
b11 .
b11 0
b11 E
1$
#14
0$
#15
b11 .
b11 0
b11 E
1$
#16
0$
0&
#17
1>
0@
0B
b100 #
b100 -
b100 /
b100 1
b100 .
b100 0
b100 E
1$
#18
0$
#19
1B
b101 #
b101 -
b101 /
b101 1
1?
0A
b100 !
b100 +
b100 2
0C
b101 .
b101 0
b101 E
1$
#20
0$
#21
1@
0B
b110 #
b110 -
b110 /
b110 1
b110 .
b110 0
b110 E
1$
0%
#22
0$
#23
1B
b111 #
b111 -
b111 /
b111 1
b111 .
b111 0
b111 E
1$
#24
0$
#25
1$
0(
#26
0$
#27
1$
#28
1A
b111 !
b111 +
b111 2
1C
0$
1%
#29
1$
#30
0$
#31
1$
#32
0$
#33
0>
0@
0B
b0 #
b0 -
b0 /
b0 1
0C
0A
b0 !
b0 +
b0 2
0?
b0 .
b0 0
b0 E
1$
1)
#34
0$
#35
1$
#36
0$
#37
1B
b1 #
b1 -
b1 /
b1 1
b1 .
b1 0
b1 E
1$
b10100001 '
b10100001 *
b10100001 D
1(
0)
#38
14
16
18
1:
0B
b11110000 #
b11110000 -
b11110000 /
b11110000 1
b10100001 .
b10100001 0
b10100001 E
0$
1&
#39
1B
b11110001 #
b11110001 -
b11110001 /
b11110001 1
1;
19
17
b1111 "
b1111 ,
b1111 3
15
b10100010 .
b10100010 0
b10100010 E
1$
0&
#40
0$
#41
1@
0B
b11110010 #
b11110010 -
b11110010 /
b11110010 1
b1 !
b1 +
b1 2
1C
b10100011 .
b10100011 0
b10100011 E
1$
#42
0$
#43
1B
b11110011 #
b11110011 -
b11110011 /
b11110011 1
0C
b10 !
b10 +
b10 2
1A
b10100100 .
b10100100 0
b10100100 E
1$
#44
0$
#45
1>
0@
0B
b11110100 #
b11110100 -
b11110100 /
b11110100 1
b11 !
b11 +
b11 2
1C
b10100101 .
b10100101 0
b10100101 E
1$
