lab8/ejercicio2/lab8_2.v
// lab 8
// ejercicio 2

module ROM(
	input logic [11:0] adress,
	output wire [7:0] data);
reg[0:11] memoria [0:4096];

initial begin
	$readmemh("memory_list", memoria);
	end
assign	data = memoria[adress];
endmodule

lab8/ejercicio2/lab8_2_tb.v
// ejercicio2 testbench
module testbench();
reg[11:0] adress;
wire[7:0] data;

ROM u1(adress, data);

initial begin
#1
$display("\n Memoria ROM");
$display("\n  adress        |    data");
$monitor(" %b  |   %b ", adress, data);
	adress = 12'b000000000000;
#1	adress = 12'b000000000100;
#1	adress = 12'b000000000010;
#1	adress = 12'b000000001100;
#1	adress = 12'b000000000010;
#1	adress = 12'b000000000100;
#1	adress = 12'b000001001001;
#1	adress = 12'b000000100111;
#1	adress = 12'b000010100011;
#1	adress = 12'b000010101111;
#1	adress = 12'b000011111111;

end

initial
	#30 $finish;
	initial begin
		$dumpfile("lab8_2.vcd");
		$dumpvars(0, testbench);
	end
endmodule

lab8/ejercicio2/lab8_2.vcd
$date
	Fri Oct 23 17:45:49 2020
$end
$version
	Icarus Verilog
$end
$timescale
	1ps
$end
$scope module testbench $end
$var wire 8 ! data [7:0] $end
$var reg 12 " adress [11:0] $end
$scope module u1 $end
$var wire 12 # adress [11:0] $end
$var wire 8 $ data [7:0] $end
$upscope $end
$upscope $end
$enddefinitions $end
#0
$dumpvars
bx $
bx #
bx "
bx !
$end
#1
b0 !
b0 $
b0 "
b0 #
#2
b100 !
b100 $
b100 "
b100 #
#3
b10 !
b10 $
b10 "
b10 #
#4
b1100 !
b1100 $
b1100 "
b1100 #
#5
b10 !
b10 $
b10 "
b10 #
#6
b100 !
b100 $
b100 "
b100 #
#7
b1001001 !
b1001001 $
b1001001 "
b1001001 #
#8
b100111 !
b100111 $
b100111 "
b100111 #
#9
b10100011 !
b10100011 $
b10100011 "
b10100011 #
#10
b10101111 !
b10101111 $
b10101111 "
b10101111 #
#11
b11111111 !
b11111111 $
b11111111 "
b11111111 #
