lab9/ejercicio 4/ej4.v
// lab 9

// ejercicio 04
// buffer triestado
module tristate_buffer(input wire c, input wire [0:3]a, output wire [0:3]y);
	assign y= c ? a : 4'bz;	
endmodule

lab9/ejercicio 4/ej4_tb.v
module testbench();

reg c;
reg [0:3]a;
wire [0:3]y;

tristate_buffer bt(c, a, y);

initial begin
#1
	$display("\n buffer triestado \n c   a   |  y");
	$monitor("%b  %b | %b  ", c, a, y);
	#1	c = 0; a = 4'b0000;
	#2	c = 1;
	#4	a = 4'b1111;
	#3	a = 4'b0101;
	#2	a = 4'b1100;
	#1	c = 0;
	#2	a = 4'b1010;
end

initial
	#45	$finish;
	initial begin
		$dumpfile("ej4.vcd");
		$dumpvars(0, testbench);
	end
endmodule

lab9/ejercicio 4/ej4.vcd
$date
	Sat Oct 31 10:59:23 2020
$end
$version
	Icarus Verilog
$end
$timescale
	1ps
$end
$scope module testbench $end
$var wire 4 ! y [0:3] $end
$var reg 4 " a [0:3] $end
$var reg 1 # c $end
$scope module bt $end
$var wire 4 $ a [0:3] $end
$var wire 1 # c $end
$var wire 4 % y [0:3] $end
$upscope $end
$upscope $end
$enddefinitions $end
#0
$dumpvars
bx %
bx $
x#
bx "
bx !
$end
#2
bz !
bz %
b0 "
b0 $
0#
#4
b0 !
b0 %
1#
#8
b1111 !
b1111 %
b1111 "
b1111 $
#11
b101 !
b101 %
b101 "
b101 $
#13
b1100 !
b1100 %
b1100 "
b1100 $
#14
bz !
bz %
0#
#16
b1010 "
b1010 $
