lab9/ejercicio 3/ej3.v
// lab 9

module flipflopD(input wire CLK, reset, D, enable, output reg Q);

always @ (posedge CLK, posedge reset, enable) begin
	if (reset) begin
		Q <= 1'b0;
	end
	else if (enable) begin
		Q <= D;
	end
end
endmodule

// ejercicio 03
// flipflop tipo jk
module	flipflopjk(input wire clk, reset, enable, j, k, output wire q);
wire d, nq, nk, and1, and2;

not	(nq, q);
not (nk, k);
and (and1, nq, j);
and (and2, nk, q);
or	(d, and1, and2);

	

	flipflopD f1(clk, reset, d, enable, q);

endmodule

lab9/ejercicio 3/ej3_tb.v
module testbench();

reg clk, reset, enable, d1, j, k;
wire	q;

flipflopjk	ft(clk, reset, enable, j, k, q);

	always
		begin
		clk <= 0; #1 clk <=1; #1;
		end

initial begin
#1
	$display("\n flipflop jk \n clk reset enable j  k | q");
	$monitor("%b     %b     %b    %b  %b | %b", clk, reset, enable, j, k, q);
	#1	reset = 1;	j = 0; k = 0; enable = 0;
	#1	reset = 0;
	#2	enable = 1;	
	#4	j = 1;
	#4	j = 0; k = 0;
	#4	k = 1; j = 1;
	#8	j = 0; k = 0;
	#4	reset = 1;
	#2	reset = 0;
	#2	j = 0; k = 1;
end

initial
	#45	$finish;
	initial begin
		$dumpfile("ej3.vcd");
		$dumpvars(0, testbench);
	end
endmodule

lab9/ejercicio 3/ej3.vcd
$date
	Sat Oct 31 10:52:08 2020
$end
$version
	Icarus Verilog
$end
$timescale
	1ps
$end
$scope module testbench $end
$var wire 1 ! q $end
$var reg 1 " clk $end
$var reg 1 # enable $end
$var reg 1 $ j $end
$var reg 1 % k $end
$var reg 1 & reset $end
$scope module ft $end
$var wire 1 ' and1 $end
$var wire 1 ( and2 $end
$var wire 1 " clk $end
$var wire 1 ) d $end
$var wire 1 # enable $end
$var wire 1 $ j $end
$var wire 1 % k $end
$var wire 1 * nk $end
$var wire 1 + nq $end
$var wire 1 & reset $end
$var wire 1 ! q $end
$scope module f1 $end
$var wire 1 " CLK $end
$var wire 1 ) D $end
$var wire 1 # enable $end
$var wire 1 & reset $end
$var reg 1 ! Q $end
$upscope $end
$upscope $end
$upscope $end
$enddefinitions $end
#0
$dumpvars
x+
x*
x)
x(
x'
x&
x%
x$
x#
0"
x!
$end
#1
1"
#2
0)
0(
1+
0!
0"
1*
0'
0#
0%
0$
1&
#3
1"
0&
#4
0"
#5
1"
1#
#6
0"
#7
1"
#8
0"
#9
1(
0+
1!
1"
1)
0'
1$
#10
0"
#11
1"
#12
0"
#13
1"
0$
#14
0"
#15
1"
#16
0"
#17
1'
1+
0!
1"
1)
0(
0*
1$
1%
#18
0"
#19
0)
0'
0+
1!
1"
#20
0"
#21
1)
1'
1+
0!
1"
#22
0"
#23
0)
0'
0+
1!
1"
#24
0"
#25
1"
1)
1(
1*
0%
0$
#26
0"
#27
1"
#28
0"
#29
0)
0(
1+
0!
1"
1&
#30
0"
#31
1"
0&
#32
0"
#33
1"
0*
1%
