lab8/lab8.v
//lab8

// ejercicio 01, contador de 12 bits

module contador(
    input clk, reset, enable, load, input[11:0]loadbits,
    output reg[11:0] count
);

always @ (posedge clk, posedge reset, posedge load) begin


if(enable) begin
    	count <= count + 1'b1;
	end

if(load) begin
	count <= loadbits;
	end

if(reset) begin
	count <= 000000000000;
	end


end
endmodule

// ejercicio 2
module ROM(
	input logic [11:0] adress,
	output wire [7:0] data);
reg[0:11] memoria [0:4095];

initial begin
	$readmemh("memory_list", memoria);
	end
assign	data = memoria[adress];
endmodule


// ejercicio 3

module alu(
           input wire [3:0] A,
           input wire [3:0] B,     
           input logic [2:0] Sel,
           output logic [3:0] out
    );
    always @(*)
    begin
        case(Sel)
        0:	
			out = A & B;
		1:	
			out = A | B;
		2:	
			out = A + B;
		3:	
			out = 4'b0000;
		4:	
			out = A & ~B;
		5:	
			out = A | ~B;
		6:	
			out = A - B;
		7:	
			out = (A < B) ? 4'b1111 : 4'b0000;
		default: 
			out = 4'b0000;
		endcase
    end

endmodule

lab8/lab8_tb.v
module testbench();
reg	clk, reset, load, enable;
reg[11:0] loadbits;
wire[11:0] count;
reg[11:0] adress;
wire[7:0] data;
reg[3:0] A;
reg[3:0] B;
reg[2:0] sel;
wire[3:0] out;

contador u1(clk, reset, enable, load,loadbits, count);
ROM 	 u2(adress, data);
alu		 u3(A, B, sel, out);

always
	begin
	clk <= 0; #1 clk <= 1; #1;
	end

initial begin
#1
	$display("\n contador 12 bits");
	$display("\n clk | reset | enable | load |    load     |   count");
	$monitor("%b       %b        %b       %b    %b      %b    ", clk, reset, enable, load, loadbits, count);
		reset = 1; enable = 0; load = 0; loadbits = 12'b100100000001;
	#1	reset = 0; 
	#2	enable = 1;
	#5	enable = 0;
	#5	enable = 1;
	#3	load = 1; 
	#8	load = 0;
	#9	reset = 1;
	#4	reset = 0;
	#4	loadbits = 12'b100000000000; enable = 0;
	#6	load = 1;
	#4	load = 0;
	#8	enable = 1;
	end


initial begin
#80
$display("\n Memoria ROM");
$display("\n  adress        |    data");
$monitor(" %b  |   %b ", adress, data);
	adress = 12'b000000000000;
#1	adress = 12'b000000000100;
#1	adress = 12'b000000000010;
#1	adress = 12'b000000001100;
#1	adress = 12'b000000000010;
#1	adress = 12'b000000000100;
#1	adress = 12'b000001001001;
#1	adress = 12'b000000100111;
#1	adress = 12'b000010100011;
#1	adress = 12'b000010101111;
#1	adress = 12'b000011111111;

end

initial begin
#120
$display("\n ALU ");
$display("\n  A    |   B    | sel  | out  ");
$monitor(" %b    %b    %b    %b ", A, B, sel, out);
	A = 4'b0101; B = 4'b0110; sel = 3'b000;
#1	A = 4'b1101; B = 4'b0010; sel = 3'b000;
#1	A = 4'b0101; B = 4'b0110; sel = 3'b001;
#1	A = 4'b1001; B = 4'b0110; sel = 3'b001;
#1	A = 4'b0101; B = 4'b0110; sel = 3'b010;
#1	A = 4'b0111; B = 4'b0100; sel = 3'b010;
#1	A = 4'b0101; B = 4'b0110; sel = 3'b011;
#1	A = 4'b0001; B = 4'b1110; sel = 3'b011;
#1	A = 4'b0101; B = 4'b0110; sel = 3'b100;
#1	A = 4'b0110; B = 4'b1000; sel = 3'b100;
#1	A = 4'b0101; B = 4'b0110; sel = 3'b101;
#1	A = 4'b0001; B = 4'b0100; sel = 3'b101;
#1	A = 4'b0101; B = 4'b0110; sel = 3'b110;
#1	A = 4'b1111; B = 4'b0001; sel = 3'b110;
#1	A = 4'b0101; B = 4'b0110; sel = 3'b111;
#1	A = 4'b1111; B = 4'b0100; sel = 3'b111;

end

initial
	#150 $finish;
	initial begin
		$dumpfile("lab8.vcd");
		$dumpvars(0, testbench);
	end
endmodule

lab8/lab8.vcd
$date
	Sat Oct 24 01:26:20 2020
$end
$version
	Icarus Verilog
$end
$timescale
	1ps
$end
$scope module testbench $end
$var wire 4 ! out [3:0] $end
$var wire 8 " data [7:0] $end
$var wire 12 # count [11:0] $end
$var reg 4 $ A [3:0] $end
$var reg 4 % B [3:0] $end
$var reg 12 & adress [11:0] $end
$var reg 1 ' clk $end
$var reg 1 ( enable $end
$var reg 1 ) load $end
$var reg 12 * loadbits [11:0] $end
$var reg 1 + reset $end
$var reg 3 , sel [2:0] $end
$scope module u1 $end
$var wire 1 ' clk $end
$var wire 1 ( enable $end
$var wire 1 ) load $end
$var wire 12 - loadbits [11:0] $end
$var wire 1 + reset $end
$var reg 12 . count [11:0] $end
$upscope $end
$scope module u2 $end
$var wire 12 / adress [11:0] $end
$var wire 8 0 data [7:0] $end
$upscope $end
$scope module u3 $end
$var wire 4 1 A [3:0] $end
$var wire 4 2 B [3:0] $end
$var wire 3 3 Sel [2:0] $end
$var reg 4 4 out [3:0] $end
$upscope $end
$upscope $end
$enddefinitions $end
#0
$dumpvars
bx 4
bx 3
bx 2
bx 1
bx 0
bx /
bx .
bx -
bx ,
x+
bx *
x)
x(
0'
bx &
bx %
bx $
bx #
bx "
bx !
$end
#1
b0 #
b0 .
1'
b100100000001 *
b100100000001 -
0)
0(
1+
#2
0'
0+
#3
1'
#4
0'
1(
#5
b1 #
b1 .
1'
#6
0'
#7
b10 #
b10 .
1'
#8
0'
#9
1'
0(
#10
0'
#11
1'
#12
0'
#13
1'
#14
0'
1(
#15
b11 #
b11 .
1'
#16
0'
#17
b100100000001 #
b100100000001 .
1'
1)
#18
0'
#19
b100100000001 #
b100100000001 .
1'
#20
0'
#21
b100100000001 #
b100100000001 .
1'
#22
0'
#23
b100100000001 #
b100100000001 .
1'
#24
0'
#25
b100100000010 #
b100100000010 .
1'
0)
#26
0'
#27
b100100000011 #
b100100000011 .
1'
#28
0'
#29
b100100000100 #
b100100000100 .
1'
#30
0'
#31
b100100000101 #
b100100000101 .
1'
#32
0'
#33
b100100000110 #
b100100000110 .
1'
#34
b0 #
b0 .
0'
1+
#35
b0 #
b0 .
1'
#36
0'
#37
b0 #
b0 .
1'
#38
0'
0+
#39
b1 #
b1 .
1'
#40
0'
#41
b10 #
b10 .
1'
#42
0'
0(
b100000000000 *
b100000000000 -
#43
1'
#44
0'
#45
1'
#46
0'
#47
1'
#48
b100000000000 #
b100000000000 .
0'
1)
#49
1'
#50
0'
#51
1'
#52
0'
0)
#53
1'
#54
0'
#55
1'
#56
0'
#57
1'
#58
0'
#59
1'
#60
0'
1(
#61
b100000000001 #
b100000000001 .
1'
#62
0'
#63
b100000000010 #
b100000000010 .
1'
#64
0'
#65
b100000000011 #
b100000000011 .
1'
#66
0'
#67
b100000000100 #
b100000000100 .
1'
#68
0'
#69
b100000000101 #
b100000000101 .
1'
#70
0'
#71
b100000000110 #
b100000000110 .
1'
#72
0'
#73
b100000000111 #
b100000000111 .
1'
#74
0'
#75
b100000001000 #
b100000001000 .
1'
#76
0'
#77
b100000001001 #
b100000001001 .
1'
#78
0'
#79
b100000001010 #
b100000001010 .
1'
#80
0'
b0 "
b0 0
b0 &
b0 /
#81
b100000001011 #
b100000001011 .
1'
b100 "
b100 0
b100 &
b100 /
#82
0'
b10 "
b10 0
b10 &
b10 /
#83
b100000001100 #
b100000001100 .
1'
b1100 "
b1100 0
b1100 &
b1100 /
#84
0'
b10 "
b10 0
b10 &
b10 /
#85
b100000001101 #
b100000001101 .
1'
b100 "
b100 0
b100 &
b100 /
#86
0'
b1001001 "
b1001001 0
b1001001 &
b1001001 /
#87
b100000001110 #
b100000001110 .
1'
b100111 "
b100111 0
b100111 &
b100111 /
#88
0'
b10100011 "
b10100011 0
b10100011 &
b10100011 /
#89
b100000001111 #
b100000001111 .
1'
b10101111 "
b10101111 0
b10101111 &
b10101111 /
#90
0'
b11111111 "
b11111111 0
b11111111 &
b11111111 /
#91
b100000010000 #
b100000010000 .
1'
#92
0'
#93
b100000010001 #
b100000010001 .
1'
#94
0'
#95
b100000010010 #
b100000010010 .
1'
#96
0'
#97
b100000010011 #
b100000010011 .
1'
#98
0'
#99
b100000010100 #
b100000010100 .
1'
#100
0'
#101
b100000010101 #
b100000010101 .
1'
#102
0'
#103
b100000010110 #
b100000010110 .
1'
#104
0'
#105
b100000010111 #
b100000010111 .
1'
#106
0'
#107
b100000011000 #
b100000011000 .
1'
#108
0'
#109
b100000011001 #
b100000011001 .
1'
#110
0'
#111
b100000011010 #
b100000011010 .
1'
#112
0'
#113
b100000011011 #
b100000011011 .
1'
#114
0'
#115
b100000011100 #
b100000011100 .
1'
#116
0'
#117
b100000011101 #
b100000011101 .
1'
#118
0'
#119
b100000011110 #
b100000011110 .
1'
#120
0'
b100 !
b100 4
b0 ,
b0 3
b110 %
b110 2
b101 $
b101 1
#121
b100000011111 #
b100000011111 .
1'
b0 !
b0 4
b10 %
b10 2
b1101 $
b1101 1
#122
0'
b111 !
b111 4
b1 ,
b1 3
b110 %
b110 2
b101 $
b101 1
#123
b100000100000 #
b100000100000 .
1'
b1111 !
b1111 4
b1001 $
b1001 1
#124
0'
b1011 !
b1011 4
b10 ,
b10 3
b101 $
b101 1
#125
b100000100001 #
b100000100001 .
1'
b100 %
b100 2
b111 $
b111 1
#126
0'
b0 !
b0 4
b11 ,
b11 3
b110 %
b110 2
b101 $
b101 1
#127
b100000100010 #
b100000100010 .
1'
b1110 %
b1110 2
b1 $
b1 1
#128
0'
b1 !
b1 4
b100 ,
b100 3
b110 %
b110 2
b101 $
b101 1
#129
b100000100011 #
b100000100011 .
1'
b110 !
b110 4
b1000 %
b1000 2
b110 $
b110 1
#130
0'
b1101 !
b1101 4
b101 ,
b101 3
b110 %
b110 2
b101 $
b101 1
#131
b100000100100 #
b100000100100 .
1'
b1011 !
b1011 4
b100 %
b100 2
b1 $
b1 1
#132
0'
b1111 !
b1111 4
b110 ,
b110 3
b110 %
b110 2
b101 $
b101 1
#133
b100000100101 #
b100000100101 .
1'
b1110 !
b1110 4
b1 %
b1 2
b1111 $
b1111 1
#134
0'
b1111 !
b1111 4
b111 ,
b111 3
b110 %
b110 2
b101 $
b101 1
#135
b100000100110 #
b100000100110 .
1'
b0 !
b0 4
b100 %
b100 2
b1111 $
b1111 1
#136
0'
#137
b100000100111 #
b100000100111 .
1'
#138
0'
#139
b100000101000 #
b100000101000 .
1'
#140
0'
#141
b100000101001 #
b100000101001 .
1'
#142
0'
#143
b100000101010 #
b100000101010 .
1'
#144
0'
#145
b100000101011 #
b100000101011 .
1'
#146
0'
#147
b100000101100 #
b100000101100 .
1'
#148
0'
#149
b100000101101 #
b100000101101 .
1'
