lab8/lab8.v
//lab8

// ejercicio 01, contador de 12 bits

module contador(
    input clk, reset, enable, load, input[11:0]loadbits,
    output reg[11:0] count
);

always @ (posedge clk, posedge reset, posedge load) begin


if(enable) begin
    	count <= count + 1'b1;
	end

if(load) begin
	count <= loadbits;
	end

if(reset) begin
	count <= 000000000000;
	end


end
endmodule

// ejercicio 2
module ROM(
	input logic [11:0] adress,
	output wire [7:0] data);
reg[0:11] memoria [0:4095];

initial begin
	$readmemh("memory_list", memoria);
	end
assign	data = memoria[adress];
endmodule


// ejercicio 3

module alu(
           input wire [3:0] A,
           input wire [3:0] B,     
           input logic [2:0] Sel,
           output logic [3:0] out
    );
    always @(*)
    begin
        case(Sel)
        0:	
			out = A & B;
		1:	
			out = A | B;
		2:	
			out = A + B;
		3:	
			out = 4'b0000;
		4:	
			out = A & ~B;
		5:	
			out = A | ~B;
		6:	
			out = A - B;
		7:	
			out = (A < B) ? 4'b1111 : 4'b0000;
		default: 
			out = 4'b0000;
		endcase
    end

endmodule

lab8/ejercicio2/lab8_2_tb.v
// ejercicio2 testbench
module testbench();
reg[11:0] adress;
wire[7:0] data;

ROM u1(adress, data);

initial begin
#1
$display("\n Memoria ROM");
$display("\n  adress        |    data");
$monitor(" %b  |   %b ", adress, data);
	adress = 12'b000000000000;
#1	adress = 12'b000000000100;
#1	adress = 12'b000000000010;
#1	adress = 12'b000000001100;
#1	adress = 12'b000000000010;
#1	adress = 12'b000000000100;
#1	adress = 12'b000001001001;
#1	adress = 12'b000000100111;
#1	adress = 12'b000010100011;
#1	adress = 12'b000010101111;
#1	adress = 12'b000011111111;

end

initial
	#30 $finish;
	initial begin
		$dumpfile("lab8_2.vcd");
		$dumpvars(0, testbench);
	end
endmodule

lab8/lab8_2.vcd
$date
	Fri Oct 23 17:17:20 2020
$end
$version
	Icarus Verilog
$end
$timescale
	1ps
$end
$scope module testbench $end
$var wire 8 ! data [7:0] $end
$var reg 12 " adress [11:0] $end
$scope module u1 $end
$var wire 12 # adress [11:0] $end
$var wire 8 $ data [7:0] $end
$upscope $end
$upscope $end
$enddefinitions $end
#0
$dumpvars
bx $
bx #
bx "
bx !
$end
#1
b0 !
b0 $
b0 "
b0 #
#2
b100 !
b100 $
b100 "
b100 #
#3
b10 !
b10 $
b10 "
b10 #
#4
b1100 !
b1100 $
b1100 "
b1100 #
#5
b10 !
b10 $
b10 "
b10 #
#6
b100 !
b100 $
b100 "
b100 #
#7
b1001001 !
b1001001 $
b1001001 "
b1001001 #
#8
b100111 !
b100111 $
b100111 "
b100111 #
#9
b10100011 !
b10100011 $
b10100011 "
b10100011 #
#10
b10101111 !
b10101111 $
b10101111 "
b10101111 #
#11
b11111111 !
b11111111 $
b11111111 "
b11111111 #
