lab8/lab8.v
//lab8

// ejercicio 01, contador de 12 bits

module contador(
    input clk, reset, enable, load, input[11:0]loadbits,
    output reg[11:0] count
);

always @ (posedge clk, posedge reset, posedge load) begin


if(enable) begin
    	count <= count + 1'b1;
	end

if(load) begin
	count <= loadbits;
	end

if(reset) begin
	count <= 000000000000;
	end


end
endmodule

// ejercicio 2
module ROM(
	input logic [11:0] adress,
	output wire [7:0] data);
reg[0:11] memoria [0:4095];

initial begin
	$readmemh("memory_list", memoria);
	end
assign	data = memoria[adress];
endmodule


// ejercicio 3

module alu(
           input wire [3:0] A,
           input wire [3:0] B,     
           input logic [2:0] Sel,
           output logic [3:0] out
    );
    always @(*)
    begin
        case(Sel)
        0:	
			out = A & B;
		1:	
			out = A | B;
		2:	
			out = A + B;
		3:	
			out = 4'b0000;
		4:	
			out = A & ~B;
		5:	
			out = A | ~B;
		6:	
			out = A - B;
		7:	
			out = (A < B) ? 4'b1111 : 4'b0000;
		default: 
			out = 4'b0000;
		endcase
    end

endmodule

lab8/ejercicio1/lab8_1_tb.v
module testbench();
reg	clk, reset, load, enable;
reg[11:0] loadbits;
wire[11:0] count;

contador u1(clk, reset, enable, load,loadbits, count);

always
	begin
	clk <= 0; #1 clk <= 1; #1;
	end

initial begin
#1
	$display("\n contador 12 bits");
	$display("\n clk | reset | enable | load |    load     |   count");
	$monitor("%b       %b        %b       %b    %b      %b    ", clk, reset, enable, load, loadbits, count);
		reset = 1; enable = 0; load = 0; loadbits = 12'b100100000001;
	#1	reset = 0; 
	#2	enable = 1;
	#5	enable = 0;
	#5	enable = 1;
	#3	load = 1; 
	#8	load = 0;
	#9	reset = 1;
	#4	reset = 0;
	#4	loadbits = 12'b100000000000; enable = 0;
	#6	load = 1;
	#4	load = 0;
	#8	enable = 1;
	end

initial
	#80 $finish;
	initial begin
		$dumpfile("lab8_1.vcd");
		$dumpvars(0, testbench);
	end
endmodule

lab8/lab8_1.vcd
$date
	Fri Oct 23 12:31:15 2020
$end
$version
	Icarus Verilog
$end
$timescale
	1ps
$end
$scope module testbench $end
$var wire 12 ! count [11:0] $end
$var reg 1 " clk $end
$var reg 1 # enable $end
$var reg 1 $ load $end
$var reg 12 % loadbits [11:0] $end
$var reg 1 & reset $end
$scope module u1 $end
$var wire 1 " clk $end
$var wire 1 # enable $end
$var wire 1 $ load $end
$var wire 12 ' loadbits [11:0] $end
$var wire 1 & reset $end
$var reg 12 ( count [11:0] $end
$upscope $end
$upscope $end
$enddefinitions $end
#0
$dumpvars
bx (
bx '
x&
bx %
x$
x#
0"
bx !
$end
#1
b0 !
b0 (
1"
b100100000001 %
b100100000001 '
0$
0#
1&
#2
0"
0&
#3
1"
#4
0"
1#
#5
b1 !
b1 (
1"
#6
0"
#7
b10 !
b10 (
1"
#8
0"
#9
1"
0#
#10
0"
#11
1"
#12
0"
#13
1"
#14
0"
1#
#15
b11 !
b11 (
1"
#16
0"
#17
b100100000001 !
b100100000001 (
1"
1$
#18
0"
#19
b100100000001 !
b100100000001 (
1"
#20
0"
#21
b100100000001 !
b100100000001 (
1"
#22
0"
#23
b100100000001 !
b100100000001 (
1"
#24
0"
#25
b100100000010 !
b100100000010 (
1"
0$
#26
0"
#27
b100100000011 !
b100100000011 (
1"
#28
0"
#29
b100100000100 !
b100100000100 (
1"
#30
0"
#31
b100100000101 !
b100100000101 (
1"
#32
0"
#33
b100100000110 !
b100100000110 (
1"
#34
b0 !
b0 (
0"
1&
#35
b0 !
b0 (
1"
#36
0"
#37
b0 !
b0 (
1"
#38
0"
0&
#39
b1 !
b1 (
1"
#40
0"
#41
b10 !
b10 (
1"
#42
0"
0#
b100000000000 %
b100000000000 '
#43
1"
#44
0"
#45
1"
#46
0"
#47
1"
#48
b100000000000 !
b100000000000 (
0"
1$
#49
1"
#50
0"
#51
1"
#52
0"
0$
#53
1"
#54
0"
#55
1"
#56
0"
#57
1"
#58
0"
#59
1"
#60
0"
1#
#61
b100000000001 !
b100000000001 (
1"
#62
0"
#63
b100000000010 !
b100000000010 (
1"
#64
0"
#65
b100000000011 !
b100000000011 (
1"
#66
0"
#67
b100000000100 !
b100000000100 (
1"
#68
0"
#69
b100000000101 !
b100000000101 (
1"
#70
0"
#71
b100000000110 !
b100000000110 (
1"
#72
0"
#73
b100000000111 !
b100000000111 (
1"
#74
0"
#75
b100000001000 !
b100000001000 (
1"
#76
0"
#77
b100000001001 !
b100000001001 (
1"
#78
0"
#79
b100000001010 !
b100000001010 (
1"
