lab3/tabla02POS/tabla02POS.v
module tabla02POS();

// POS del tabla02POS

  reg A, B, C;
  wire w1, w2, w3, w4, w5, out, wa, wb, wc;

  // not (salida, entrada);
  // and (salida, entrada1, entrada2, entrada3, etc);
  
  not U1(wa, A);
  not U2(wb, B);
  not U3(wc, C);
  or U4(w1, A, B, C);
  or U5(w2, A, wb, C);
  or U6(w3, A, wb,wc);
  or U7(w4, wa, B, C);
  or U8(w5, wa, B, wc);
  and U9(out, w1, w2, w3, w4, w5);



  initial begin
    $display("A B C | Y");
    $display("-------");
    $monitor("%b %b %b | %b", A, B, C, out);
    A = 0; B = 0; C=0;
    #1 C = 1;
    #1 B = 1;
    C = 0;
    #1 B = 1;
    C = 1;
    #1 A = 1;
    B = 0;
    C = 0;
     #1 C = 1;
    #1 B = 1;
    C = 0;
    #1 B = 1;
    C = 1;
    #1 $finish;
  end

  initial 
    begin
      $dumpfile("tabla02POS.vcd"); 
      $dumpvars(0, tabla02POS);
    end 

endmodule

lab3/tabla02POS/tabla02POS.vcd
$date
	Sun Aug  2 14:22:15 2020
$end
$version
	Icarus Verilog
$end
$timescale
	1ps
$end
$scope module tabla02POS $end
$var wire 1 ! out $end
$var wire 1 " w1 $end
$var wire 1 # w2 $end
$var wire 1 $ w3 $end
$var wire 1 % w4 $end
$var wire 1 & w5 $end
$var wire 1 ' wa $end
$var wire 1 ( wb $end
$var wire 1 ) wc $end
$var reg 1 * A $end
$var reg 1 + B $end
$var reg 1 , C $end
$upscope $end
$enddefinitions $end
#0
$dumpvars
0,
0+
0*
1)
1(
1'
1&
1%
1$
1#
0"
0!
$end
#1
1!
1"
0)
1,
#2
0!
0#
1)
0(
0,
1+
#3
0$
1#
0)
1,
#4
1)
1&
0%
1(
1$
0'
0,
0+
1*
#5
0&
1%
0)
1,
#6
1!
1)
1&
0(
0,
1+
#7
0)
1,
