lab3/tabla04POS/tabla04POS.v
module tabla04POS();

// POS del tabla04

  reg A, B, C, D;
  wire w1, w2, w3, w4, w5, w6, w7, w8, w9, out, wa, wb, wc, wd;

  // not (salida, entrada);
  // and (salida, entrada1, entrada2, entrada3, etc);
  
  not U1(wa, A);
  not U2(wb, B);
  not U3(wc, C);
  not U4(wd, D);
  or U5(w1, A, B, C, wd);
  or U6(w2, A, wb, C, D);
  or U7(w3, A, wb, C, wd);
  or U8(w4, wa, B, C, wd);
  or U9(w5, wa, B, wc, wd);
  or U10(w6, wa, wb, C, D);
  or U11(w7, wa, wb, C, wd);
  or U12(w8, wa, wb, wc, D);
  or U13(w9, wa, wb, wc, wd);
  and U14(out, w1, w2, w3,w4, w5, w6, w7, w8, w9);


  initial begin
    $display("A B C D| Y");
    $display("-------");
    $monitor("%b %b %b %b| %b", A, B, C, D, out);
    A = 0; B = 0; C=0; D=0;
    #1 D = 1;
    #1 C = 1; D = 0;
    #1 D = 1;
    #1 B = 1; C = 0; D = 0;
    #1 D = 1;
    #1 C = 1; D = 0;
    #1 D = 1;
    #1 A = 1; B = 0; C = 0; D = 0;
    #1 D = 1;
    #1 C = 1; D = 0;
    #1 D = 1;
    #1 B = 1; C = 0; D = 0;
    #1 D = 1;
    #1 C = 1; D = 0;
    #1 D = 1;
    #1 $finish;
  end

  initial begin
      $dumpfile("tabla04POS.vcd"); 
      $dumpvars(0, tabla04POS);
    end 

endmodule

lab3/tabla04POS/tabla04POS.vcd
$date
	Sun Aug  2 14:48:09 2020
$end
$version
	Icarus Verilog
$end
$timescale
	1ps
$end
$scope module tabla04POS $end
$var wire 1 ! out $end
$var wire 1 " w1 $end
$var wire 1 # w2 $end
$var wire 1 $ w3 $end
$var wire 1 % w4 $end
$var wire 1 & w5 $end
$var wire 1 ' w6 $end
$var wire 1 ( w7 $end
$var wire 1 ) w8 $end
$var wire 1 * w9 $end
$var wire 1 + wa $end
$var wire 1 , wb $end
$var wire 1 - wc $end
$var wire 1 . wd $end
$var reg 1 / A $end
$var reg 1 0 B $end
$var reg 1 1 C $end
$var reg 1 2 D $end
$upscope $end
$enddefinitions $end
#0
$dumpvars
02
01
00
0/
1.
1-
1,
1+
1*
1)
1(
1'
1&
1%
1$
1#
1"
1!
$end
#1
0!
0"
0.
12
#2
1!
1.
1"
0-
02
11
#3
0.
12
#4
0!
1.
1$
0#
1-
0,
02
01
10
#5
0$
1#
0.
12
#6
1!
1.
1$
0-
02
11
#7
0.
12
#8
1!
1.
1-
1&
1%
1,
0+
02
01
00
1/
#9
0!
0%
0.
12
#10
1!
1.
1%
0-
02
11
#11
0!
0&
0.
12
#12
1.
1(
0'
1-
1&
0,
02
01
10
#13
0(
1'
0.
12
#14
0)
1.
1(
0-
02
11
#15
0*
1)
0.
12
