lab9/ejercicio 5/ej5.v
// lab 9

module ROM(
	input wire [6:0] address,
	output reg [12:0] data);

	always @ ( * ) begin
    casex (address)
    7'bxxxxxx0: //0
      data <= 13'b1000000001000;
    7'b00001x1: //1
      data <= 13'b0100000001000;
    7'b00000x1: //2
      data <= 13'b1000000001000;
    7'b00011x1: //3
      data <= 13'b1000000001000;
    7'b00010x1: //4
      data <= 13'b0100000001000;
    7'b0010xx1: //5
      data <= 13'b0001001000010;
    7'b0011xx1: //6
      data <= 13'b1001001100000;
    7'b0100xx1: //7
      data <= 13'b0011010000010;
    7'b0101xx1: //8
      data <= 13'b0011010000100;
    7'b0110xx1: //9
      data <= 13'b1011010100000;
    7'b0111xx1: //10
      data <= 13'b1000000111000;
    7'b1000x11: //11
      data <= 13'b0100000001000;
    7'b1000x01: //12
      data <= 13'b1000000001000;
    7'b1001x11: //13
      data <= 13'b1000000001000;
    7'b1001x01: //14
      data <= 13'b0100000001000;
    7'b1010xx1: //15
      data <= 13'b0011011000010;
    7'b1011xx1: //16
      data <= 13'b1011011100000;
    7'b1100xx1: //17
      data <= 13'b0100000001000;
    7'b1101xx1: //18
      data <= 13'b0000000001001;
    7'b1110xx1: //19
      data <= 13'b0011100000010;
    7'b1111xx1: //20
      data <= 13'b1011100100000;
    default:
      data <= 13'b0;
    endcase
    end
endmodule

lab9/ejercicio 5/ej5_tb.v
module testbench();

reg [6:0] address;
wire [12:0] data;

ROM		ugh(address, data);

initial begin
#1
	$display("\n ejercicio 5 \n  address |      data");
	$monitor("%b | %b ", address, data);
		address = 7'bxxxxxx0;
	#2	address = 7'b00001x1;
	#2	address = 7'b00000x1;
	#2	address = 7'b00011x1;
	#2	address = 7'b00010x1;
	#2	address = 7'b0010xx1;
	#2	address = 7'b0011xx1;
	#2	address = 7'b0100xx1;
	#2	address = 7'b0101xx1;
	#2	address = 7'b0110xx1;
	#2	address = 7'b0111xx1;
	#2	address = 7'b1000x11;
	#2	address = 7'b1000x01;
	#2	address = 7'b1001x11;
	#2	address = 7'b1001x01;
	#2	address = 7'b1010xx1;
	#2	address = 7'b1011xx1;
	#2	address = 7'b1100xx1;
	#2	address = 7'b1101xx1;
	#2	address = 7'b1110xx1;
	#2	address = 7'b1111xx1;
		// sin x
	#2	address = 7'b1111110;
	#2	address = 7'b0000111;
	#2	address = 7'b0000001;
	#2	address = 7'b0001111;
	#2	address = 7'b0001011;
	#2	address = 7'b0010001;
	#2	address = 7'b0011101;
end


initial
	#60	$finish;
	initial begin
		$dumpfile("ej5.vcd");
		$dumpvars(0, testbench);
	end
endmodule

lab9/ejercicio 5/ej5.vcd
$date
	Sat Oct 31 11:17:13 2020
$end
$version
	Icarus Verilog
$end
$timescale
	1ps
$end
$scope module testbench $end
$var wire 13 ! data [12:0] $end
$var reg 7 " address [6:0] $end
$scope module ugh $end
$var wire 7 # address [6:0] $end
$var reg 13 $ data [12:0] $end
$upscope $end
$upscope $end
$enddefinitions $end
#0
$dumpvars
bx $
bx #
bx "
bx !
$end
#1
b1000000001000 !
b1000000001000 $
bx0 "
bx0 #
#3
b100000001000 !
b100000001000 $
b1x1 "
b1x1 #
#5
b1000000001000 !
b1000000001000 $
b0x1 "
b0x1 #
#7
b11x1 "
b11x1 #
#9
b100000001000 !
b100000001000 $
b10x1 "
b10x1 #
#11
b1001000010 !
b1001000010 $
b10xx1 "
b10xx1 #
#13
b1001001100000 !
b1001001100000 $
b11xx1 "
b11xx1 #
#15
b11010000010 !
b11010000010 $
b100xx1 "
b100xx1 #
#17
b11010000100 !
b11010000100 $
b101xx1 "
b101xx1 #
#19
b1011010100000 !
b1011010100000 $
b110xx1 "
b110xx1 #
#21
b1000000111000 !
b1000000111000 $
b111xx1 "
b111xx1 #
#23
b100000001000 !
b100000001000 $
b1000x11 "
b1000x11 #
#25
b1000000001000 !
b1000000001000 $
b1000x01 "
b1000x01 #
#27
b1001x11 "
b1001x11 #
#29
b100000001000 !
b100000001000 $
b1001x01 "
b1001x01 #
#31
b11011000010 !
b11011000010 $
b1010xx1 "
b1010xx1 #
#33
b1011011100000 !
b1011011100000 $
b1011xx1 "
b1011xx1 #
#35
b100000001000 !
b100000001000 $
b1100xx1 "
b1100xx1 #
#37
b1001 !
b1001 $
b1101xx1 "
b1101xx1 #
#39
b11100000010 !
b11100000010 $
b1110xx1 "
b1110xx1 #
#41
b1011100100000 !
b1011100100000 $
b1111xx1 "
b1111xx1 #
#43
b1000000001000 !
b1000000001000 $
b1111110 "
b1111110 #
#45
b100000001000 !
b100000001000 $
b111 "
b111 #
#47
b1000000001000 !
b1000000001000 $
b1 "
b1 #
#49
b1111 "
b1111 #
#51
b100000001000 !
b100000001000 $
b1011 "
b1011 #
#53
b1001000010 !
b1001000010 $
b10001 "
b10001 #
#55
b1001001100000 !
b1001001100000 $
b11101 "
b11101 #
