lab3/tabla01SOP/tabla01SOP.v
module tabla01SOP();

// SOP del tabla01SOP

  reg A, B, C;
  wire w1, w2, w3, w4, w5, out, wa, wb, wc;

  // not (salida, entrada);
  // and (salida, entrada1, entrada2, entrada3, etc);
  
  not U1(wa, A);
  not U2(wb, B);
  not U3(wc, C);
  and U4(w1, wa, wb, wc);
  and U5(w2, wa, B, wc);
  and U6(w3, A, wb, wc);
  and U7(w4, A, wb, C);
  and U8(w5, A, B, C);
  or U9(out, w1, w2, w3, w4, w5);


  initial begin
    $display("A B C | Y");
    $display("-------");
    $monitor("%b %b %b | %b", A, B, C, out);
    A = 0; B = 0; C=0;
    #1 C = 1;
    #1 B = 1;
    C = 0;
    #1 B = 1;
    C = 1;
    #1 A = 1;
    B = 0;
    C = 0;
     #1 C = 1;
    #1 B = 1;
    C = 0;
    #1 B = 1;
    C = 1;
    #1 $finish;
  end

  initial begin
      $dumpfile("tabla01SOP.vcd"); 
      $dumpvars(0, tabla01SOP);
    end 

endmodule

lab3/tabla01SOP/tabla01SOP.vcd
$date
	Sun Aug  2 14:10:46 2020
$end
$version
	Icarus Verilog
$end
$timescale
	1ps
$end
$scope module tabla01SOP $end
$var wire 1 ! out $end
$var wire 1 " w1 $end
$var wire 1 # w2 $end
$var wire 1 $ w3 $end
$var wire 1 % w4 $end
$var wire 1 & w5 $end
$var wire 1 ' wa $end
$var wire 1 ( wb $end
$var wire 1 ) wc $end
$var reg 1 * A $end
$var reg 1 + B $end
$var reg 1 , C $end
$upscope $end
$enddefinitions $end
#0
$dumpvars
0,
0+
0*
1)
1(
1'
0&
0%
0$
0#
1"
1!
$end
#1
0!
0"
0)
1,
#2
1!
1#
1)
0(
0,
1+
#3
0!
0#
0)
1,
#4
1!
1$
1)
1(
0'
0,
0+
1*
#5
0$
1%
0)
1,
#6
0!
0%
1)
0(
0,
1+
#7
1!
1&
0)
1,
