Proyecto/impresora.v
// FSM proyecto

module flipflop(input CLK, reset, input D, output reg Q);
always @ (posedge CLK, posedge reset) begin
	if(reset) begin
		Q <= 0;
	end
	else
		Q <= D;
	end
endmodule

module antirebote(input wire prendido, boton, clk, reset, output y);
	wire s0, s1;
	wire sf0, sf1;

	assign	sf1 = boton;
	assign	sf0 = s1 & (~boton);

	flipflop	U1(clk, reset, sf0, s0);
	flipflop	U2(clk, reset, sf1, s1);

	assign	y = s0 & prendido;

endmodule

module escaner(input wire antirebote, clk, reset, input wire[0:1]ajustes, output imp_color, negro, escaner);
	wire s0, s1;
	wire sf0, sf1;

	assign	sf1 = ( ~s0 & ajustes[1] & antirebote ) | (antirebote & ~s0 & ~ajustes[0]) | (s1);
	assign	sf0 = s0 | (antirebote & ajustes[0] & ~s0);

	flipflop	U1(clk, reset, sf0, s0);
	flipflop	U2(clk, reset, sf1, s1);

	assign	imp_color = s0 & s1;
	assign	negro = s0 & ~s1;
	assign	escaner = ~s0 & s1;

endmodule

module bandera(input wire prendido, boton, clk, reset, output y);
	wire s0, s1;
	wire sf0, sf1;

	assign	sf0 = (s0 & boton) | (s1);
	assign	sf1 = boton & ~s0 & ~s1;

	flipflop	U1(clk, reset, sf0, s0);
	flipflop	U2(clk, reset, sf1, s1);

	assign	y = s1 & prendido;
endmodule

module tinta(input wire imprimir, prendido, clk, reset, output error, output wire[0:6]y);
	wire s0, s1, s2, s3;
	wire sf0, sf1, sf2, sf3;

	assign	sf0 = (imprimir & s1 & s2 & s3) | s0;

	assign	sf1 = (imprimir & s2 & s3) | s1;

	assign	sf2 = (imprimir & ~s2 & s3) | (~imprimir & s2) | (imprimir & s1 & s2 & s3) | (s2 & ~s3);

	assign	sf3 = (imprimir & s1 & s2 & s3) | (imprimir & ~s3) | (~imprimir & s3);


 
	flipflop	U1(clk, reset, sf0, s0);
	flipflop	U2(clk, reset, sf1, s1);
	flipflop	U3(clk, reset, sf2, s2);
	flipflop	U4(clk, reset, sf3, s3);

	assign	error = s0;

	assign	y[0] = prendido & ((~s1 & s3) | (s1 & ~s2) | (~s1 & s2 & ~s3));
	assign 	y[1] = prendido & ((~s1 & s2 & ~s3) | (s2 & s3) | (~s1 & ~s2 & s3));
	assign 	y[2] = prendido & ((~s2 & ~s3) | (~s1 & s2 & ~s3) | (~s1 & ~s2 & s3) | (s1 & s3));
	assign	y[3] = prendido & ((s1 & s2) | (~s2 & ~s3) | (s2 & s3) | (s1 & s3));
	assign	y[4] = prendido & ((~s1 & ~s2 & s3) | (s1 & s3));
	assign 	y[5] = prendido & ((s1 & ~s2) | (~s1 & s2 & ~s3) | (~s1 & ~s2 & s3) | (s1 & s3));
	assign 	y[6] = prendido & ((s1 & s2) | (~s2 & ~s3) | (~s1 & s2 & ~s3) | (s2 & s3) | (~s1 & ~s2 & s3));
endmodule

module impresora(input wire error, color, clk, reset, input wire[0:1]pagina, output imprimir, fin);
	wire s0, s1, s2, s3;
	wire sf0, sf1, sf2, sf3;

	assign	sf0 = (~s0 & ~s2 & s3 & error) | (~s0 & ~s1 & s2) | (s0 & s1) | (~s0 & s1 & ~s3);
	assign	sf1 = (~s0 & ~s1 & ~s2 & color & pagina[1] & pagina[0]) | (s0 & ~s1 & s2 & s3) | (~s0 & s2 & ~s3 & error)  | (~s0 & ~s2 & s3 & error) | (~s0 & ~s2 & s3 & ~error)  | (~s0 & s2 & s3 & error) | (s1 & error) | (~s0 & s1 & s3);
	assign	sf2 = (~s0 & ~s2 & ~s3 & color & pagina[1] & ~pagina[0]) | (~s0 & ~s2 & ~s3 & color & ~pagina[1] & pagina[0]) | (s0 & ~s1 & ~s2 & s3) | (~s0 & ~s2 & s3 & ~error) | (s0 & s2 & ~s3) | (~s0 & s2 & s3 & error) | (s1 & s2) | (~s0 & s1 & ~s3) | (~s0 & s1 & s3);
	assign	sf3 = (~s1 & ~s2 & ~s3 & color & ~pagina[0]) | (~s0 & s2 & ~s3 & error) | (s0 & ~s1 & ~s3) | (~s0 & s3 & ~error) | (~s0 & s1 & error) | (s1 & s3);



	flipflop	U1(clk, reset, sf0, s0);
	flipflop	U2(clk, reset, sf1, s1);
	flipflop	U3(clk, reset, sf2, s2);
	flipflop	U4(clk, reset, sf3, s3);


	assign	fin = ~s0 & s1 & s2 & s3;
	assign	imprimir = s0 & ~s1;

endmodule

module	senales(input wire prendido, color, escanear, imprimir, input wire[0:1]ajustes_escaner, input wire reset, clk, rellenar_color, rellenar_negro, input wire[0:1]paginas, output wire  esc_escaner, fin_color, fin_negro, output wire[0:6]display1, output wire[0:6]display2);
	wire	b_escanear, b_imprimir, esc_color, esc_negro, senal_negra, senal_color, senal_contador_n, senal_contador_c, imprimir1_c, imprimir1_n, error1, error2;


	antirebote	antirebote_escaner(prendido, escanear, clk, reset, b_escanear);
	escaner 	escaner(b_escanear, clk, reset, ajustes_escaner, esc_color, esc_negro, esc_escaner);

	bandera		mandar_imprimir_color(prendido, esc_color, clk, reset, imprimir1_c);
	bandera		mandar_imprimir_negro(prendido, esc_negro, clk, reset, imprimir1_n);

	antirebote	antirebote_impresora(prendido, imprimir, clk, reset, b_imprimir);
	assign	negro_imp = b_imprimir & ~color;
	assign	color_imp = b_imprimir & color;

	assign	senal_negra = imprimir1_n | negro_imp;
	assign	senal_color = imprimir1_c | color_imp;

	assign	senal_contador_n = senal_negra | imprimirr_n;
	assign	senal_contador_c = senal_color | imprimirr_c;



	impresora 	impresoracolor(error1, senal_color, clk, reset, paginas, imprimirr_c, fin_color);
	tinta		tintacolor(senal_contador_c, prendido, clk, rellenar_color, error1, display1);

	impresora 	impresoranegra(error2, senal_negra, clk, reset, paginas, imprimirr_n, fin_negro);
	tinta		tintanegra(senal_contador_n, prendido, clk, rellenar_negro, error2, display2);


endmodule

Proyecto/impresora_tb.v
module testbench();
reg clk, reset, clk1;
reg imprimir, escanear, color, prendido;
reg[0:1] paginas;
reg[0:1] ajustes_escaner;
reg  rellenar_color, rellenar_negro, volver;
wire fin_escaner, fin_color, fin_negro;
wire[0:6] display1;
wire[0:6] display2;
wire imprimirc, fin;
wire	imprimir1_c, imprimir1_n, esc_escaner;


senales		bb(prendido, color, escanear, imprimir, ajustes_escaner, reset, clk, rellenar_color, rellenar_negro, paginas, esc_escaner, fin_color, fin_negro, display1, display2);


	always
		begin
		clk <= 0; reset <=0; #1 clk <= 1; #1;
		end


initial begin
	#1
		$display("\n \n	impresora");
		$display("\n");
		$display("on ajustes reset rell imp pag esc col rell display1 display2 ");
    	$monitor("%b  %b     %b    %b  %b   %b    %b    %b   %b   %b   %b ", prendido, ajustes_escaner, reset, rellenar_color, imprimir, paginas, escanear, color, rellenar_negro, display1, display2);
prendido = 1; ajustes_escaner = 11; reset = 1; rellenar_color = 1;  imprimir = 0; paginas = 11; escanear = 0; color = 0; rellenar_negro = 1;
#2	reset = 0; rellenar_color = 0; rellenar_negro = 0;
#2	escanear = 1;
#8	escanear = 0;
#30	reset = 1;
#2	reset = 0;

#2	escanear = 1; 
#11	escanear = 0;
#22	rellenar_color = 1;
#2	rellenar_color = 0;
#8	reset = 1; 
#5	reset = 0;
#1	ajustes_escaner = 01;

#4	escanear = 1; 
#2	escanear = 0; paginas = 00;
#12	reset = 1; 
#5	reset = 0; 
#2	escanear = 1; 
#2	escanear = 0;
#10	ajustes_escaner = 10;

#20	reset = 1;
#5	reset = 0;
#1	color = 1; paginas = 01;
#2	imprimir = 1;
#2	imprimir = 0;
#12	reset = 1;
#5	reset = 0;
#1	color = 0; paginas = 00;
#2	imprimir = 1; 
#2	imprimir = 0;

#1	rellenar_color = 1; rellenar_negro = 1;
#1	rellenar_color = 0; rellenar_negro = 0;

#20	escanear = 1; 
#2	escanear = 0; paginas = 11;
#12	reset = 1; 
#5	reset = 0; 
#2	escanear = 1; 
#2	escanear = 0;
#10	ajustes_escaner = 10;

#25	reset = 1;
#5	reset = 0;
#1	color = 0; paginas = 11;
#2	imprimir = 1;
#2	imprimir = 0;
#12	reset = 1;
#5	reset = 0;
#1	color = 0; paginas = 00;
#2	imprimir = 1; 
#2	imprimir = 0;


end

initial
	#350	$finish;
	initial begin
		$dumpfile("impresora.vcd");
		$dumpvars(0, testbench);
	end

endmodule

Proyecto/impresora.vcd
$date
	Sun Oct 11 23:04:13 2020
$end
$version
	Icarus Verilog
$end
$timescale
	1ps
$end
$scope module testbench $end
$var wire 1 ! fin_negro $end
$var wire 1 " fin_color $end
$var wire 1 # esc_escaner $end
$var wire 7 $ display2 [0:6] $end
$var wire 7 % display1 [0:6] $end
$var reg 2 & ajustes_escaner [0:1] $end
$var reg 1 ' clk $end
$var reg 1 ( color $end
$var reg 1 ) escanear $end
$var reg 1 * imprimir $end
$var reg 2 + paginas [0:1] $end
$var reg 1 , prendido $end
$var reg 1 - rellenar_color $end
$var reg 1 . rellenar_negro $end
$var reg 1 / reset $end
$scope module bb $end
$var wire 2 0 ajustes_escaner [0:1] $end
$var wire 1 ' clk $end
$var wire 1 ( color $end
$var wire 1 1 color_imp $end
$var wire 1 ) escanear $end
$var wire 1 * imprimir $end
$var wire 1 2 negro_imp $end
$var wire 2 3 paginas [0:1] $end
$var wire 1 , prendido $end
$var wire 1 - rellenar_color $end
$var wire 1 . rellenar_negro $end
$var wire 1 / reset $end
$var wire 1 4 senal_color $end
$var wire 1 5 senal_contador_c $end
$var wire 1 6 senal_contador_n $end
$var wire 1 7 senal_negra $end
$var wire 1 8 imprimirr_n $end
$var wire 1 9 imprimirr_c $end
$var wire 1 : imprimir1_n $end
$var wire 1 ; imprimir1_c $end
$var wire 1 ! fin_negro $end
$var wire 1 " fin_color $end
$var wire 1 < esc_negro $end
$var wire 1 # esc_escaner $end
$var wire 1 = esc_color $end
$var wire 1 > error2 $end
$var wire 1 ? error1 $end
$var wire 7 @ display2 [0:6] $end
$var wire 7 A display1 [0:6] $end
$var wire 1 B b_imprimir $end
$var wire 1 C b_escanear $end
$scope module antirebote_escaner $end
$var wire 1 ) boton $end
$var wire 1 ' clk $end
$var wire 1 , prendido $end
$var wire 1 / reset $end
$var wire 1 D sf0 $end
$var wire 1 E sf1 $end
$var wire 1 C y $end
$var wire 1 F s1 $end
$var wire 1 G s0 $end
$scope module U1 $end
$var wire 1 ' CLK $end
$var wire 1 D D $end
$var wire 1 / reset $end
$var reg 1 G Q $end
$upscope $end
$scope module U2 $end
$var wire 1 ' CLK $end
$var wire 1 E D $end
$var wire 1 / reset $end
$var reg 1 F Q $end
$upscope $end
$upscope $end
$scope module antirebote_impresora $end
$var wire 1 * boton $end
$var wire 1 ' clk $end
$var wire 1 , prendido $end
$var wire 1 / reset $end
$var wire 1 H sf0 $end
$var wire 1 I sf1 $end
$var wire 1 B y $end
$var wire 1 J s1 $end
$var wire 1 K s0 $end
$scope module U1 $end
$var wire 1 ' CLK $end
$var wire 1 H D $end
$var wire 1 / reset $end
$var reg 1 K Q $end
$upscope $end
$scope module U2 $end
$var wire 1 ' CLK $end
$var wire 1 I D $end
$var wire 1 / reset $end
$var reg 1 J Q $end
$upscope $end
$upscope $end
$scope module escaner $end
$var wire 2 L ajustes [0:1] $end
$var wire 1 C antirebote $end
$var wire 1 ' clk $end
$var wire 1 # escaner $end
$var wire 1 = imp_color $end
$var wire 1 < negro $end
$var wire 1 / reset $end
$var wire 1 M sf0 $end
$var wire 1 N sf1 $end
$var wire 1 O s1 $end
$var wire 1 P s0 $end
$scope module U1 $end
$var wire 1 ' CLK $end
$var wire 1 M D $end
$var wire 1 / reset $end
$var reg 1 P Q $end
$upscope $end
$scope module U2 $end
$var wire 1 ' CLK $end
$var wire 1 N D $end
$var wire 1 / reset $end
$var reg 1 O Q $end
$upscope $end
$upscope $end
$scope module impresoracolor $end
$var wire 1 ' clk $end
$var wire 1 4 color $end
$var wire 1 " fin $end
$var wire 1 9 imprimir $end
$var wire 2 Q pagina [0:1] $end
$var wire 1 / reset $end
$var wire 1 R sf0 $end
$var wire 1 S sf1 $end
$var wire 1 T sf2 $end
$var wire 1 U sf3 $end
$var wire 1 V s3 $end
$var wire 1 W s2 $end
$var wire 1 X s1 $end
$var wire 1 Y s0 $end
$var wire 1 ? error $end
$scope module U1 $end
$var wire 1 ' CLK $end
$var wire 1 R D $end
$var wire 1 / reset $end
$var reg 1 Y Q $end
$upscope $end
$scope module U2 $end
$var wire 1 ' CLK $end
$var wire 1 S D $end
$var wire 1 / reset $end
$var reg 1 X Q $end
$upscope $end
$scope module U3 $end
$var wire 1 ' CLK $end
$var wire 1 T D $end
$var wire 1 / reset $end
$var reg 1 W Q $end
$upscope $end
$scope module U4 $end
$var wire 1 ' CLK $end
$var wire 1 U D $end
$var wire 1 / reset $end
$var reg 1 V Q $end
$upscope $end
$upscope $end
$scope module impresoranegra $end
$var wire 1 ' clk $end
$var wire 1 7 color $end
$var wire 1 ! fin $end
$var wire 1 8 imprimir $end
$var wire 2 Z pagina [0:1] $end
$var wire 1 / reset $end
$var wire 1 [ sf0 $end
$var wire 1 \ sf1 $end
$var wire 1 ] sf2 $end
$var wire 1 ^ sf3 $end
$var wire 1 _ s3 $end
$var wire 1 ` s2 $end
$var wire 1 a s1 $end
$var wire 1 b s0 $end
$var wire 1 > error $end
$scope module U1 $end
$var wire 1 ' CLK $end
$var wire 1 [ D $end
$var wire 1 / reset $end
$var reg 1 b Q $end
$upscope $end
$scope module U2 $end
$var wire 1 ' CLK $end
$var wire 1 \ D $end
$var wire 1 / reset $end
$var reg 1 a Q $end
$upscope $end
$scope module U3 $end
$var wire 1 ' CLK $end
$var wire 1 ] D $end
$var wire 1 / reset $end
$var reg 1 ` Q $end
$upscope $end
$scope module U4 $end
$var wire 1 ' CLK $end
$var wire 1 ^ D $end
$var wire 1 / reset $end
$var reg 1 _ Q $end
$upscope $end
$upscope $end
$scope module mandar_imprimir_color $end
$var wire 1 = boton $end
$var wire 1 ' clk $end
$var wire 1 , prendido $end
$var wire 1 / reset $end
$var wire 1 c sf0 $end
$var wire 1 d sf1 $end
$var wire 1 ; y $end
$var wire 1 e s1 $end
$var wire 1 f s0 $end
$scope module U1 $end
$var wire 1 ' CLK $end
$var wire 1 c D $end
$var wire 1 / reset $end
$var reg 1 f Q $end
$upscope $end
$scope module U2 $end
$var wire 1 ' CLK $end
$var wire 1 d D $end
$var wire 1 / reset $end
$var reg 1 e Q $end
$upscope $end
$upscope $end
$scope module mandar_imprimir_negro $end
$var wire 1 < boton $end
$var wire 1 ' clk $end
$var wire 1 , prendido $end
$var wire 1 / reset $end
$var wire 1 g sf0 $end
$var wire 1 h sf1 $end
$var wire 1 : y $end
$var wire 1 i s1 $end
$var wire 1 j s0 $end
$scope module U1 $end
$var wire 1 ' CLK $end
$var wire 1 g D $end
$var wire 1 / reset $end
$var reg 1 j Q $end
$upscope $end
$scope module U2 $end
$var wire 1 ' CLK $end
$var wire 1 h D $end
$var wire 1 / reset $end
$var reg 1 i Q $end
$upscope $end
$upscope $end
$scope module tintacolor $end
$var wire 1 ' clk $end
$var wire 1 ? error $end
$var wire 1 5 imprimir $end
$var wire 1 , prendido $end
$var wire 1 - reset $end
$var wire 1 k sf0 $end
$var wire 1 l sf1 $end
$var wire 1 m sf2 $end
$var wire 1 n sf3 $end
$var wire 7 o y [0:6] $end
$var wire 1 p s3 $end
$var wire 1 q s2 $end
$var wire 1 r s1 $end
$var wire 1 s s0 $end
$scope module U1 $end
$var wire 1 ' CLK $end
$var wire 1 k D $end
$var wire 1 - reset $end
$var reg 1 s Q $end
$upscope $end
$scope module U2 $end
$var wire 1 ' CLK $end
$var wire 1 l D $end
$var wire 1 - reset $end
$var reg 1 r Q $end
$upscope $end
$scope module U3 $end
$var wire 1 ' CLK $end
$var wire 1 m D $end
$var wire 1 - reset $end
$var reg 1 q Q $end
$upscope $end
$scope module U4 $end
$var wire 1 ' CLK $end
$var wire 1 n D $end
$var wire 1 - reset $end
$var reg 1 p Q $end
$upscope $end
$upscope $end
$scope module tintanegra $end
$var wire 1 ' clk $end
$var wire 1 > error $end
$var wire 1 6 imprimir $end
$var wire 1 , prendido $end
$var wire 1 . reset $end
$var wire 1 t sf0 $end
$var wire 1 u sf1 $end
$var wire 1 v sf2 $end
$var wire 1 w sf3 $end
$var wire 7 x y [0:6] $end
$var wire 1 y s3 $end
$var wire 1 z s2 $end
$var wire 1 { s1 $end
$var wire 1 | s0 $end
$scope module U1 $end
$var wire 1 ' CLK $end
$var wire 1 t D $end
$var wire 1 . reset $end
$var reg 1 | Q $end
$upscope $end
$scope module U2 $end
$var wire 1 ' CLK $end
$var wire 1 u D $end
$var wire 1 . reset $end
$var reg 1 { Q $end
$upscope $end
$scope module U3 $end
$var wire 1 ' CLK $end
$var wire 1 v D $end
$var wire 1 . reset $end
$var reg 1 z Q $end
$upscope $end
$scope module U4 $end
$var wire 1 ' CLK $end
$var wire 1 w D $end
$var wire 1 . reset $end
$var reg 1 y Q $end
$upscope $end
$upscope $end
$upscope $end
$upscope $end
$enddefinitions $end
#0
$dumpvars
x|
x{
xz
xy
bx x
xw
xv
xu
xt
xs
xr
xq
xp
bx o
xn
xm
xl
xk
xj
xi
xh
xg
xf
xe
xd
xc
xb
xa
x`
x_
x^
x]
x\
x[
bx Z
xY
xX
xW
xV
xU
xT
xS
xR
bx Q
xP
xO
xN
xM
bx L
xK
xJ
xI
xH
xG
xF
xE
xD
xC
xB
bx A
bx @
x?
x>
x=
x<
x;
x:
x9
x8
x7
x6
x5
x4
bx 3
x2
x1
bx 0
0/
x.
x-
x,
bx +
x*
x)
x(
0'
bx &
bx %
bx $
x#
x"
x!
$end
#1
0S
0\
0T
0]
0n
0w
0U
0^
0N
0M
b11001 $
b11001 @
b11001 x
b11001 %
b11001 A
b11001 o
0d
05
0h
06
0R
0[
0v
0m
0c
04
0g
07
02
0t
0u
0k
0l
0C
0D
0<
0#
0=
0;
0:
0B
0H
09
0"
08
0!
0>
0|
0{
0z
0y
0?
0s
0r
0q
0p
0G
0F
0P
0O
0f
0e
0j
0i
0K
0J
0Y
0X
0W
0V
0b
0a
0`
0_
1'
01
1.
0(
0E
0)
b11 +
b11 3
b11 Q
b11 Z
0I
0*
1-
1/
b11 &
b11 0
b11 L
1,
#2
0/
0'
#3
1'
0.
0-
#4
0'
#5
1F
1'
1E
1)
#6
0'
#7
1'
#8
0'
#9
1'
#10
0'
#11
1'
#12
0'
#13
1N
1M
1C
0F
1G
1'
0D
0E
0)
#14
0'
#15
1d
0C
0#
1=
0G
1P
1O
1'
#16
0'
#17
1S
1n
15
14
0d
1;
1c
1e
1'
#18
0'
#19
0S
1T
1n
0m
05
1R
b1110111 %
b1110111 A
b1110111 o
04
0d
0;
1c
1f
0e
1X
1p
1'
#20
0'
#21
1m
1U
0n
1T
15
0R
19
1W
0X
1Y
1'
#22
0'
#23
0S
0T
1R
0n
b1110011 %
b1110011 A
b1110011 o
05
09
0Y
1V
1q
0p
1'
#24
0'
#25
1T
0U
1n
0R
15
19
0W
1Y
1'
#26
0'
#27
0T
1R
b1101001 %
b1101001 A
b1101001 o
1n
1m
05
0l
09
0Y
1W
0V
1p
1'
#28
0'
#29
0m
1U
1l
0n
0R
15
19
0W
1Y
1'
#30
0'
#31
1S
1T
b1011011 %
b1011011 A
b1011011 o
0n
05
09
0Y
1V
1r
0q
0p
1'
#32
0'
#33
0R
1"
1W
1X
1'
#34
0'
#35
1'
#36
0'
#37
1'
#38
0'
#39
1'
#40
0'
#41
1'
#42
0'
#43
0U
0T
0c
0S
0M
0=
0N
0"
0P
0O
0f
0X
0W
0V
1'
1/
#44
0/
0'
#45
1'
#46
0'
#47
1F
1'
1E
1)
#48
0'
#49
1'
#50
0'
#51
1'
#52
0'
#53
1'
#54
0'
#55
1'
#56
0'
#57
1'
#58
0'
1D
0E
0)
#59
1N
1M
0D
1C
0F
1G
1'
#60
0'
#61
1d
0C
0#
1=
0G
1P
1O
1'
#62
0'
#63
1S
1n
15
14
0d
1;
1c
1e
1'
#64
0'
#65
0S
1T
1n
0m
05
1R
b1011110 %
b1011110 A
b1011110 o
04
0d
0;
1c
1f
0e
1X
1p
1'
#66
0'
#67
1m
1U
0n
1T
15
0R
19
1W
0X
1Y
1'
#68
0'
#69
0S
0T
1R
0n
b1001 %
b1001 A
b1001 o
05
09
0Y
1V
0p
1q
1'
#70
0'
#71
1T
0U
1n
0R
15
19
0W
1Y
1'
#72
0'
#73
0T
1R
b111111 %
b111111 A
b111111 o
05
0k
09
0Y
1W
0V
1p
1'
#74
0'
#75
1k
1U
1n
0R
15
19
0W
1Y
1'
#76
0'
#77
1S
0T
1R
0U
05
09
0Y
1V
1?
1s
1'
#78
0'
#79
0U
1n
05
09
0V
1X
1Y
1'
#80
0m
b11001 %
b11001 A
b11001 o
0S
0n
0l
0k
0p
0q
0r
0?
0s
0'
1-
#81
1U
1n
15
0R
19
0X
1'
#82
0'
0-
#83
1T
1S
1n
0m
b1110111 %
b1110111 A
b1110111 o
05
09
1V
0Y
1p
1'
#84
0'
#85
0R
1"
1X
1W
1'
#86
0'
#87
1'
#88
0'
#89
1'
#90
0U
0T
0S
0c
0"
0N
0=
0M
0V
0W
0X
0f
0O
0P
0'
0/
#91
1'
#92
0'
#93
1'
#94
0'
#95
1'
#96
0'
b1 &
b1 0
b1 L
#97
1'
#98
0'
#99
1'
#100
0'
1E
1)
#101
1F
1'
#102
0'
1D
b0 +
b0 3
b0 Q
b0 Z
0E
0)
#103
1N
1C
0D
1G
0F
1'
#104
0'
#105
1#
0C
1O
0G
1'
#106
0'
#107
1'
#108
0'
#109
1'
#110
0'
#111
1'
#112
0'
#113
1'
#114
0#
0N
0O
0'
0/
#115
1'
#116
0'
#117
1'
#118
0'
#119
1'
#120
0'
#121
1F
1'
1E
1)
#122
0'
#123
1N
1C
0F
1G
1'
0D
0E
0)
#124
0'
#125
0C
1#
0G
1O
1'
#126
0'
#127
1'
#128
0'
#129
1'
#130
0'
#131
1'
#132
0'
#133
1'
b10 &
b10 0
b10 L
#134
0'
#135
1'
#136
0'
#137
1'
#138
0'
#139
1'
#140
0'
#141
1'
#142
0'
#143
1'
#144
0'
#145
1'
#146
0'
#147
1'
#148
0'
#149
1'
#150
0'
#151
1'
#152
0'
#153
0#
0N
0O
1'
1/
#154
0/
0'
#155
1'
#156
0'
#157
1'
#158
0'
#159
1'
b1 +
b1 3
b1 Q
b1 Z
1(
#160
0'
#161
1J
1'
1I
1*
#162
0'
#163
1T
1U
1m
0n
15
14
11
1B
1K
0J
1'
0H
0I
0*
#164
0'
#165
0T
0S
1R
05
0n
04
b1110011 %
b1110011 A
b1110011 o
01
0B
1V
1W
0K
1q
0p
1'
#166
0'
#167
1T
0U
1n
0R
15
19
1Y
0W
1'
#168
0'
#169
0T
1R
b1101001 %
b1101001 A
b1101001 o
1n
1m
05
0l
09
0V
1W
0Y
1p
1'
#170
0'
#171
0m
1U
1l
0n
0R
15
19
1Y
0W
1'
#172
0'
#173
1T
1S
b1011011 %
b1011011 A
b1011011 o
0n
05
09
1V
0Y
1r
0q
0p
1'
#174
0'
#175
0T
0S
0U
0V
1'
1/
#176
0/
0'
#177
1'
#178
0'
#179
1'
#180
0'
#181
1'
b0 +
b0 3
b0 Q
b0 Z
0(
#182
0'
#183
1J
1'
1I
1*
#184
0'
#185
1^
1w
16
17
12
1B
1K
0J
1'
0H
0I
0*
#186
b11001 %
b11001 A
b11001 o
0l
0r
0'
1.
1-
#187
1]
1\
06
1w
0v
07
b1110111 $
b1110111 @
b1110111 x
02
0B
1_
0K
1y
1'
0.
0-
#188
0'
#189
0[
1!
1a
1`
1'
#190
0'
#191
1'
#192
0'
#193
1'
#194
0'
#195
1'
#196
0'
#197
1'
#198
0'
#199
1'
#200
0'
#201
1'
#202
0'
#203
1'
#204
0'
#205
1'
#206
0'
#207
1F
1'
1E
1)
#208
0'
#209
1M
1C
1G
0F
1'
0D
b11 +
b11 3
b11 Q
b11 Z
0E
0)
#210
0'
#211
1h
1<
0C
1P
0G
1'
#212
0'
#213
1v
0w
16
17
0h
1:
1g
1i
1'
#214
0'
#215
0w
06
b1110011 $
b1110011 @
b1110011 x
07
0:
0i
1j
0y
1z
1'
#216
0'
#217
1'
#218
0'
#219
1'
#220
0'
#221
0^
0]
0g
0\
0<
0M
0!
0P
0j
0a
0`
0_
1'
1/
#222
0/
0'
#223
1'
#224
0'
#225
1'
#226
0'
#227
1'
#228
0'
1E
1)
#229
1F
1'
#230
0'
1D
0E
0)
#231
1M
1C
0D
1G
0F
1'
#232
0'
#233
1h
1<
0C
1P
0G
1'
#234
0'
#235
1\
1w
16
17
0h
1:
1g
1i
1'
#236
0'
#237
0\
1]
b1101001 $
b1101001 @
b1101001 x
1w
1[
06
1v
07
0u
0:
1a
0i
1j
1y
1'
#238
0'
#239
0v
1^
1u
0w
1]
0[
16
18
1b
0a
1`
1'
#240
0'
#241
0\
0]
1[
b1011011 $
b1011011 @
b1011011 x
0w
06
08
1_
0b
1{
0z
0y
1'
#242
0'
#243
1]
0^
1w
0[
16
18
1b
0`
1'
#244
0'
#245
0]
1[
1w
0v
b1011110 $
b1011110 @
b1011110 x
06
08
0_
1`
0b
1y
1'
#246
0'
#247
1v
1^
0w
0[
16
18
1b
0`
1'
#248
0'
#249
1]
1\
0w
b1001 $
b1001 @
b1001 x
06
08
1_
0b
1z
0y
1'
#250
0'
#251
0[
1!
1a
1`
1'
#252
0'
#253
1'
#254
0'
#255
1'
#256
0'
#257
1'
#258
0'
#259
1'
#260
0'
#261
1'
#262
0'
#263
1'
#264
0'
#265
0^
0]
0\
0g
0!
0<
0M
0_
0`
0a
0j
0P
1'
1/
#266
0/
0'
#267
1'
#268
0'
#269
1'
#270
0'
#271
1'
#272
0'
#273
1J
1'
1I
1*
#274
0'
#275
1\
1w
16
17
12
1B
0J
1K
1'
0H
0I
0*
#276
0'
#277
0\
06
1]
07
1[
b111111 $
b111111 @
b111111 x
02
0t
0B
0K
1a
1y
1'
#278
0'
#279
1t
1^
1w
1]
16
0[
18
1`
0a
1b
1'
#280
0'
#281
1\
1]
1[
0^
06
08
0b
1_
1>
1|
1'
#282
0'
#283
0^
1w
06
08
0_
1a
1b
1'
#284
0'
#285
1'
#286
0'
#287
0]
0\
0[
0`
0a
0b
1'
1/
#288
0/
0'
#289
1'
#290
0'
#291
1'
#292
0'
#293
1'
b0 +
b0 3
b0 Q
b0 Z
#294
0'
#295
1J
1'
1I
1*
#296
0'
#297
1^
1w
16
17
12
1B
0J
1K
1'
0H
0I
0*
#298
0'
#299
0^
1\
1[
06
07
02
0B
0K
1_
1'
#300
0'
#301
0^
1w
06
08
0_
1a
1b
1'
